{
  "ticker": "ISRG",
  "name": "Intuitive Surgical Inc.",
  "sector": "pharma",
  "classification": "",
  "latest_annual": {
    "ticker": "ISRG",
    "period": "FY2025",
    "is_annual": true,
    "fiscal_year": 2025,
    "fiscal_quarter": null,
    "segments": [
      {
        "segment_name": "Instruments and accessories",
        "value": 6018900000.0,
        "unit": "USD",
        "period": "2025-12-31 (FY)",
        "concept": "xbrl_dimension",
        "is_annual": true
      },
      {
        "segment_name": "Systems",
        "value": 2473700000.0,
        "unit": "USD",
        "period": "2025-12-31 (FY)",
        "concept": "xbrl_dimension",
        "is_annual": true
      },
      {
        "segment_name": "Services",
        "value": 1572100000.0,
        "unit": "USD",
        "period": "2025-12-31 (FY)",
        "concept": "xbrl_dimension",
        "is_annual": true
      }
    ],
    "total_revenue": 10064700000.0,
    "gross_profit": 6642300000.0,
    "operating_income": 2945500000.0,
    "net_income": 2876600000.0,
    "rd_expense": 1311800000.0,
    "sga_expense": 2385000000.0,
    "cogs": 3422400000.0,
    "interest_expense": null,
    "income_tax": 434800000.0,
    "currency": "USD",
    "extraction_method": "xbrl",
    "confidence": 1.0,
    "notes": []
  },
  "annual_periods": [
    {
      "ticker": "ISRG",
      "period": "FY2025",
      "is_annual": true,
      "fiscal_year": 2025,
      "fiscal_quarter": null,
      "segments": [
        {
          "segment_name": "Instruments and accessories",
          "value": 6018900000.0,
          "unit": "USD",
          "period": "2025-12-31 (FY)",
          "concept": "xbrl_dimension",
          "is_annual": true
        },
        {
          "segment_name": "Systems",
          "value": 2473700000.0,
          "unit": "USD",
          "period": "2025-12-31 (FY)",
          "concept": "xbrl_dimension",
          "is_annual": true
        },
        {
          "segment_name": "Services",
          "value": 1572100000.0,
          "unit": "USD",
          "period": "2025-12-31 (FY)",
          "concept": "xbrl_dimension",
          "is_annual": true
        }
      ],
      "total_revenue": 10064700000.0,
      "gross_profit": 6642300000.0,
      "operating_income": 2945500000.0,
      "net_income": 2876600000.0,
      "rd_expense": 1311800000.0,
      "sga_expense": 2385000000.0,
      "cogs": 3422400000.0,
      "interest_expense": null,
      "income_tax": 434800000.0,
      "currency": "USD",
      "extraction_method": "xbrl",
      "confidence": 1.0,
      "notes": []
    },
    {
      "ticker": "ISRG",
      "period": "FY2024",
      "is_annual": true,
      "fiscal_year": 2024,
      "fiscal_quarter": null,
      "segments": [
        {
          "segment_name": "Instruments and accessories",
          "value": 5079000000.0,
          "unit": "USD",
          "period": "2024-12-31 (FY)",
          "concept": "xbrl_dimension",
          "is_annual": true
        },
        {
          "segment_name": "Systems",
          "value": 1966000000.0,
          "unit": "USD",
          "period": "2024-12-31 (FY)",
          "concept": "xbrl_dimension",
          "is_annual": true
        },
        {
          "segment_name": "Services",
          "value": 1307100000.0,
          "unit": "USD",
          "period": "2024-12-31 (FY)",
          "concept": "xbrl_dimension",
          "is_annual": true
        }
      ],
      "total_revenue": 8352100000.0,
      "gross_profit": 5634200000.0,
      "operating_income": 2348900000.0,
      "net_income": 2337500000.0,
      "rd_expense": 1145300000.0,
      "sga_expense": 2140000000.0,
      "cogs": 2717900000.0,
      "interest_expense": null,
      "income_tax": 336300000.0,
      "currency": "USD",
      "extraction_method": "xbrl",
      "confidence": 1.0,
      "notes": []
    },
    {
      "ticker": "ISRG",
      "period": "FY2023",
      "is_annual": true,
      "fiscal_year": 2023,
      "fiscal_quarter": null,
      "segments": [
        {
          "segment_name": "Instruments and accessories",
          "value": 4276600000.0,
          "unit": "USD",
          "period": "2023-12-31 (FY)",
          "concept": "xbrl_dimension",
          "is_annual": true
        },
        {
          "segment_name": "Systems",
          "value": 1679700000.0,
          "unit": "USD",
          "period": "2023-12-31 (FY)",
          "concept": "xbrl_dimension",
          "is_annual": true
        },
        {
          "segment_name": "Services",
          "value": 1167800000.0,
          "unit": "USD",
          "period": "2023-12-31 (FY)",
          "concept": "xbrl_dimension",
          "is_annual": true
        }
      ],
      "total_revenue": 7124100000.0,
      "gross_profit": 4729500000.0,
      "operating_income": 1766800000.0,
      "net_income": 1817300000.0,
      "rd_expense": 998800000.0,
      "sga_expense": 1963900000.0,
      "cogs": 2394600000.0,
      "interest_expense": null,
      "income_tax": 141600000.0,
      "currency": "USD",
      "extraction_method": "xbrl",
      "confidence": 1.0,
      "notes": []
    }
  ],
  "quarterly_periods": [
    {
      "ticker": "ISRG",
      "period": "2026Q1",
      "is_annual": false,
      "fiscal_year": 2026,
      "fiscal_quarter": 1,
      "segments": [
        {
          "segment_name": "Instruments and accessories",
          "value": 1686400000.0,
          "unit": "USD",
          "period": "2026-03-31 (Q1)",
          "concept": "xbrl_dimension",
          "is_annual": true
        },
        {
          "segment_name": "Systems",
          "value": 650700000.0,
          "unit": "USD",
          "period": "2026-03-31 (Q1)",
          "concept": "xbrl_dimension",
          "is_annual": true
        },
        {
          "segment_name": "Service - U.S.",
          "value": 281700000.0,
          "unit": "USD",
          "period": "2026-03-31 (Q1)",
          "concept": "xbrl_dimension",
          "is_annual": true
        },
        {
          "segment_name": "Service - Outside of the U.S. (“OUS”)",
          "value": 152000000.0,
          "unit": "USD",
          "period": "2026-03-31 (Q1)",
          "concept": "xbrl_dimension",
          "is_annual": true
        }
      ],
      "total_revenue": 2770800000.0,
      "gross_profit": 1830500000.0,
      "operating_income": 855300000.0,
      "net_income": 826000000.0,
      "rd_expense": 361900000.0,
      "sga_expense": 613300000.0,
      "cogs": 940300000.0,
      "interest_expense": null,
      "income_tax": 114400000.0,
      "currency": "USD",
      "extraction_method": "xbrl",
      "confidence": 1.0,
      "notes": []
    },
    {
      "ticker": "ISRG",
      "period": "2025Q4",
      "is_annual": false,
      "fiscal_year": 2025,
      "fiscal_quarter": 4,
      "segments": [],
      "total_revenue": 2866200000.0,
      "gross_profit": 1904300000.0,
      "operating_income": 864300000.0,
      "net_income": 794800000.0,
      "rd_expense": 352900000.0,
      "sga_expense": 687100000.0,
      "cogs": 961900000.0,
      "interest_expense": null,
      "income_tax": 156100000.0,
      "currency": "USD",
      "extraction_method": "yahoo_quarterly",
      "confidence": 0.55,
      "notes": []
    },
    {
      "ticker": "ISRG",
      "period": "2025Q3",
      "is_annual": false,
      "fiscal_year": 2025,
      "fiscal_quarter": 3,
      "segments": [
        {
          "segment_name": "Instruments and accessories",
          "value": 1518800000.0,
          "unit": "USD",
          "period": "2025-09-30 (Q3)",
          "concept": "xbrl_dimension",
          "is_annual": true
        },
        {
          "segment_name": "Systems",
          "value": 590400000.0,
          "unit": "USD",
          "period": "2025-09-30 (Q3)",
          "concept": "xbrl_dimension",
          "is_annual": true
        },
        {
          "segment_name": "Service - U.S.",
          "value": 258100000.0,
          "unit": "USD",
          "period": "2025-09-30 (Q3)",
          "concept": "xbrl_dimension",
          "is_annual": true
        },
        {
          "segment_name": "Service - Outside of the U.S. (“OUS”)",
          "value": 137800000.0,
          "unit": "USD",
          "period": "2025-09-30 (Q3)",
          "concept": "xbrl_dimension",
          "is_annual": true
        }
      ],
      "total_revenue": 2505100000.0,
      "gross_profit": 1662400000.0,
      "operating_income": 759700000.0,
      "net_income": 709200000.0,
      "rd_expense": 329400000.0,
      "sga_expense": 573300000.0,
      "cogs": 842700000.0,
      "interest_expense": null,
      "income_tax": 146000000.0,
      "currency": "USD",
      "extraction_method": "xbrl",
      "confidence": 1.0,
      "notes": []
    },
    {
      "ticker": "ISRG",
      "period": "2025Q2",
      "is_annual": false,
      "fiscal_year": 2025,
      "fiscal_quarter": 2,
      "segments": [
        {
          "segment_name": "Instruments and accessories",
          "value": 1474100000.0,
          "unit": "USD",
          "period": "2025-06-30 (Q2)",
          "concept": "xbrl_dimension",
          "is_annual": true
        },
        {
          "segment_name": "Systems",
          "value": 574700000.0,
          "unit": "USD",
          "period": "2025-06-30 (Q2)",
          "concept": "xbrl_dimension",
          "is_annual": true
        },
        {
          "segment_name": "Service - U.S.",
          "value": 258100000.0,
          "unit": "USD",
          "period": "2025-06-30 (Q2)",
          "concept": "xbrl_dimension",
          "is_annual": true
        },
        {
          "segment_name": "Service - Outside of the U.S. (“OUS”)",
          "value": 133100000.0,
          "unit": "USD",
          "period": "2025-06-30 (Q2)",
          "concept": "xbrl_dimension",
          "is_annual": true
        }
      ],
      "total_revenue": 2440000000.0,
      "gross_profit": 1617900000.0,
      "operating_income": 743400000.0,
      "net_income": 664200000.0,
      "rd_expense": 313300000.0,
      "sga_expense": 561200000.0,
      "cogs": 822100000.0,
      "interest_expense": null,
      "income_tax": 167900000.0,
      "currency": "USD",
      "extraction_method": "xbrl",
      "confidence": 1.0,
      "notes": []
    },
    {
      "ticker": "ISRG",
      "period": "2025Q1",
      "is_annual": false,
      "fiscal_year": 2025,
      "fiscal_quarter": 1,
      "segments": [
        {
          "segment_name": "Instruments and accessories",
          "value": 1367700000.0,
          "unit": "USD",
          "period": "2025-03-31 (Q1)",
          "concept": "xbrl_dimension",
          "is_annual": true
        },
        {
          "segment_name": "Systems",
          "value": 522700000.0,
          "unit": "USD",
          "period": "2025-03-31 (Q1)",
          "concept": "xbrl_dimension",
          "is_annual": true
        },
        {
          "segment_name": "Service - U.S.",
          "value": 238500000.0,
          "unit": "USD",
          "period": "2025-03-31 (Q1)",
          "concept": "xbrl_dimension",
          "is_annual": true
        },
        {
          "segment_name": "Service - Outside of the U.S. (“OUS”)",
          "value": 124500000.0,
          "unit": "USD",
          "period": "2025-03-31 (Q1)",
          "concept": "xbrl_dimension",
          "is_annual": true
        }
      ],
      "total_revenue": 2253400000.0,
      "gross_profit": 1457700000.0,
      "operating_income": 578100000.0,
      "net_income": 703700000.0,
      "rd_expense": 316200000.0,
      "sga_expense": 563400000.0,
      "cogs": 795700000.0,
      "interest_expense": null,
      "income_tax": 35200000.0,
      "currency": "USD",
      "extraction_method": "xbrl",
      "confidence": 1.0,
      "notes": []
    },
    {
      "ticker": "ISRG",
      "period": "2024Q3",
      "is_annual": false,
      "fiscal_year": 2024,
      "fiscal_quarter": 3,
      "segments": [
        {
          "segment_name": "Instruments and accessories",
          "value": 1264200000.0,
          "unit": "USD",
          "period": "2024-09-30 (Q3)",
          "concept": "xbrl_dimension",
          "is_annual": true
        },
        {
          "segment_name": "Systems",
          "value": 445000000.0,
          "unit": "USD",
          "period": "2024-09-30 (Q3)",
          "concept": "xbrl_dimension",
          "is_annual": true
        },
        {
          "segment_name": "Service - U.S.",
          "value": 209200000.0,
          "unit": "USD",
          "period": "2024-09-30 (Q3)",
          "concept": "xbrl_dimension",
          "is_annual": true
        },
        {
          "segment_name": "Service - Outside of the U.S. (“OUS”)",
          "value": 119700000.0,
          "unit": "USD",
          "period": "2024-09-30 (Q3)",
          "concept": "xbrl_dimension",
          "is_annual": true
        }
      ],
      "total_revenue": 2038100000.0,
      "gross_profit": 1373900000.0,
      "operating_income": 577300000.0,
      "net_income": 570600000.0,
      "rd_expense": 286000000.0,
      "sga_expense": 510600000.0,
      "cogs": 664200000.0,
      "interest_expense": null,
      "income_tax": 100400000.0,
      "currency": "USD",
      "extraction_method": "xbrl",
      "confidence": 1.0,
      "notes": [
        "Warning: total_revenue (2038100000) differs from Yahoo (8352100000) by 75.6%"
      ]
    },
    {
      "ticker": "ISRG",
      "period": "2024Q2",
      "is_annual": false,
      "fiscal_year": 2024,
      "fiscal_quarter": 2,
      "segments": [
        {
          "segment_name": "Instruments and accessories",
          "value": 1244400000.0,
          "unit": "USD",
          "period": "2024-06-30 (Q2)",
          "concept": "xbrl_dimension",
          "is_annual": true
        },
        {
          "segment_name": "Systems",
          "value": 448200000.0,
          "unit": "USD",
          "period": "2024-06-30 (Q2)",
          "concept": "xbrl_dimension",
          "is_annual": true
        },
        {
          "segment_name": "Services",
          "value": 317300000.0,
          "unit": "USD",
          "period": "2024-06-30 (Q2)",
          "concept": "xbrl_dimension",
          "is_annual": true
        }
      ],
      "total_revenue": 2009900000.0,
      "gross_profit": 1372700000.0,
      "operating_income": 567300000.0,
      "net_income": 531500000.0,
      "rd_expense": 280100000.0,
      "sga_expense": 525300000.0,
      "cogs": 637200000.0,
      "interest_expense": null,
      "income_tax": 123000000.0,
      "currency": "USD",
      "extraction_method": "xbrl",
      "confidence": 1.0,
      "notes": [
        "Warning: total_revenue (2009900000) differs from Yahoo (8352100000) by 75.9%"
      ]
    },
    {
      "ticker": "ISRG",
      "period": "2024Q1",
      "is_annual": false,
      "fiscal_year": 2024,
      "fiscal_quarter": 1,
      "segments": [
        {
          "segment_name": "Instruments and accessories",
          "value": 1158900000.0,
          "unit": "USD",
          "period": "2024-03-31 (Q1)",
          "concept": "xbrl_dimension",
          "is_annual": true
        },
        {
          "segment_name": "Systems",
          "value": 418200000.0,
          "unit": "USD",
          "period": "2024-03-31 (Q1)",
          "concept": "xbrl_dimension",
          "is_annual": true
        },
        {
          "segment_name": "Services",
          "value": 313500000.0,
          "unit": "USD",
          "period": "2024-03-31 (Q1)",
          "concept": "xbrl_dimension",
          "is_annual": true
        }
      ],
      "total_revenue": 1890600000.0,
      "gross_profit": 1245400000.0,
      "operating_income": 469400000.0,
      "net_income": 547400000.0,
      "rd_expense": 284500000.0,
      "sga_expense": 491500000.0,
      "cogs": 645200000.0,
      "interest_expense": null,
      "income_tax": 8900000.0,
      "currency": "USD",
      "extraction_method": "xbrl",
      "confidence": 1.0,
      "notes": [
        "Warning: total_revenue (1890600000) differs from Yahoo (8352100000) by 77.4%"
      ]
    },
    {
      "ticker": "ISRG",
      "period": "2023Q3",
      "is_annual": false,
      "fiscal_year": 2023,
      "fiscal_quarter": 3,
      "segments": [
        {
          "segment_name": "Instruments and accessories",
          "value": 1071400000.0,
          "unit": "USD",
          "period": "2023-09-30 (Q3)",
          "concept": "xbrl_dimension",
          "is_annual": true
        },
        {
          "segment_name": "Systems",
          "value": 379400000.0,
          "unit": "USD",
          "period": "2023-09-30 (Q3)",
          "concept": "xbrl_dimension",
          "is_annual": true
        },
        {
          "segment_name": "Services",
          "value": 292900000.0,
          "unit": "USD",
          "period": "2023-09-30 (Q3)",
          "concept": "xbrl_dimension",
          "is_annual": true
        }
      ],
      "total_revenue": 1743700000.0,
      "gross_profit": 1167200000.0,
      "operating_income": 465800000.0,
      "net_income": 419800000.0,
      "rd_expense": 249400000.0,
      "sga_expense": 452000000.0,
      "cogs": 576500000.0,
      "interest_expense": null,
      "income_tax": 102200000.0,
      "currency": "USD",
      "extraction_method": "xbrl",
      "confidence": 1.0,
      "notes": [
        "Warning: total_revenue (1743700000) differs from Yahoo (7124100000) by 75.5%"
      ]
    },
    {
      "ticker": "ISRG",
      "period": "2023Q2",
      "is_annual": false,
      "fiscal_year": 2023,
      "fiscal_quarter": 2,
      "segments": [
        {
          "segment_name": "Instruments and accessories",
          "value": 1075900000.0,
          "unit": "USD",
          "period": "2023-06-30 (Q2)",
          "concept": "xbrl_dimension",
          "is_annual": true
        },
        {
          "segment_name": "Systems",
          "value": 392700000.0,
          "unit": "USD",
          "period": "2023-06-30 (Q2)",
          "concept": "xbrl_dimension",
          "is_annual": true
        },
        {
          "segment_name": "Services",
          "value": 287300000.0,
          "unit": "USD",
          "period": "2023-06-30 (Q2)",
          "concept": "xbrl_dimension",
          "is_annual": true
        }
      ],
      "total_revenue": 1755900000.0,
      "gross_profit": 1171900000.0,
      "operating_income": 463200000.0,
      "net_income": 426000000.0,
      "rd_expense": 244400000.0,
      "sga_expense": 464300000.0,
      "cogs": 584000000.0,
      "interest_expense": null,
      "income_tax": 73200000.0,
      "currency": "USD",
      "extraction_method": "xbrl",
      "confidence": 1.0,
      "notes": [
        "Warning: total_revenue (1755900000) differs from Yahoo (7124100000) by 75.4%"
      ]
    }
  ],
  "ttm_revenue": 10582100000.0,
  "ttm_operating_income": 3222700000.0,
  "ttm_net_income": 2994200000.0,
  "segment_trend": {
    "Instruments and accessories": [
      {
        "period": "2023Q2",
        "value": 1075900000.0,
        "is_annual": false
      },
      {
        "period": "2023Q3",
        "value": 1071400000.0,
        "is_annual": false
      },
      {
        "period": "2024Q1",
        "value": 1158900000.0,
        "is_annual": false
      },
      {
        "period": "2024Q2",
        "value": 1244400000.0,
        "is_annual": false
      },
      {
        "period": "2024Q3",
        "value": 1264200000.0,
        "is_annual": false
      },
      {
        "period": "2025Q1",
        "value": 1367700000.0,
        "is_annual": false
      },
      {
        "period": "2025Q2",
        "value": 1474100000.0,
        "is_annual": false
      },
      {
        "period": "2025Q3",
        "value": 1518800000.0,
        "is_annual": false
      },
      {
        "period": "2026Q1",
        "value": 1686400000.0,
        "is_annual": false
      },
      {
        "period": "FY2023",
        "value": 4276600000.0,
        "is_annual": true
      },
      {
        "period": "FY2024",
        "value": 5079000000.0,
        "is_annual": true
      },
      {
        "period": "FY2025",
        "value": 6018900000.0,
        "is_annual": true
      }
    ],
    "Systems": [
      {
        "period": "2023Q2",
        "value": 392700000.0,
        "is_annual": false
      },
      {
        "period": "2023Q3",
        "value": 379400000.0,
        "is_annual": false
      },
      {
        "period": "2024Q1",
        "value": 418200000.0,
        "is_annual": false
      },
      {
        "period": "2024Q2",
        "value": 448200000.0,
        "is_annual": false
      },
      {
        "period": "2024Q3",
        "value": 445000000.0,
        "is_annual": false
      },
      {
        "period": "2025Q1",
        "value": 522700000.0,
        "is_annual": false
      },
      {
        "period": "2025Q2",
        "value": 574700000.0,
        "is_annual": false
      },
      {
        "period": "2025Q3",
        "value": 590400000.0,
        "is_annual": false
      },
      {
        "period": "2026Q1",
        "value": 650700000.0,
        "is_annual": false
      },
      {
        "period": "FY2023",
        "value": 1679700000.0,
        "is_annual": true
      },
      {
        "period": "FY2024",
        "value": 1966000000.0,
        "is_annual": true
      },
      {
        "period": "FY2025",
        "value": 2473700000.0,
        "is_annual": true
      }
    ],
    "Services": [
      {
        "period": "2023Q2",
        "value": 287300000.0,
        "is_annual": false
      },
      {
        "period": "2023Q3",
        "value": 292900000.0,
        "is_annual": false
      },
      {
        "period": "2024Q1",
        "value": 313500000.0,
        "is_annual": false
      },
      {
        "period": "2024Q2",
        "value": 317300000.0,
        "is_annual": false
      },
      {
        "period": "FY2023",
        "value": 1167800000.0,
        "is_annual": true
      },
      {
        "period": "FY2024",
        "value": 1307100000.0,
        "is_annual": true
      },
      {
        "period": "FY2025",
        "value": 1572100000.0,
        "is_annual": true
      }
    ],
    "Service - U.S.": [
      {
        "period": "2024Q3",
        "value": 209200000.0,
        "is_annual": false
      },
      {
        "period": "2025Q1",
        "value": 238500000.0,
        "is_annual": false
      },
      {
        "period": "2025Q2",
        "value": 258100000.0,
        "is_annual": false
      },
      {
        "period": "2025Q3",
        "value": 258100000.0,
        "is_annual": false
      },
      {
        "period": "2026Q1",
        "value": 281700000.0,
        "is_annual": false
      }
    ],
    "Service - Outside of the U.S. (“OUS”)": [
      {
        "period": "2024Q3",
        "value": 119700000.0,
        "is_annual": false
      },
      {
        "period": "2025Q1",
        "value": 124500000.0,
        "is_annual": false
      },
      {
        "period": "2025Q2",
        "value": 133100000.0,
        "is_annual": false
      },
      {
        "period": "2025Q3",
        "value": 137800000.0,
        "is_annual": false
      },
      {
        "period": "2026Q1",
        "value": 152000000.0,
        "is_annual": false
      }
    ]
  },
  "annual_count": 3,
  "quarterly_count": 10,
  "has_partial_data": true,
  "data_notes": [
    "Only 3/3 annual reports available"
  ]
}