{
  "ticker": "TSM",
  "name": "Taiwan Semiconductor",
  "latest_annual": {
    "ticker": "TSM",
    "period": "FY2025",
    "is_annual": true,
    "fiscal_year": 2025,
    "fiscal_quarter": null,
    "segments": [
      {
        "segment_name": "Others",
        "value": 536500800000.0,
        "unit": "USD",
        "period": "2025-12-31 (FY)",
        "concept": "xbrl_dimension",
        "is_annual": true
      },
      {
        "segment_name": "Wafer",
        "value": 3272553500000.0,
        "unit": "USD",
        "period": "2025-12-31 (FY)",
        "concept": "xbrl_dimension",
        "is_annual": true
      }
    ],
    "total_revenue": null,
    "gross_profit": 2281294000000.0,
    "operating_income": null,
    "net_income": 1695124900000.0,
    "rd_expense": 246427200000.0,
    "sga_expense": null,
    "cogs": null,
    "interest_expense": null,
    "income_tax": null,
    "currency": "USD",
    "extraction_method": "xbrl",
    "confidence": 0.59,
    "notes": []
  },
  "annual_periods": [
    {
      "ticker": "TSM",
      "period": "FY2025",
      "is_annual": true,
      "fiscal_year": 2025,
      "fiscal_quarter": null,
      "segments": [
        {
          "segment_name": "Others",
          "value": 536500800000.0,
          "unit": "USD",
          "period": "2025-12-31 (FY)",
          "concept": "xbrl_dimension",
          "is_annual": true
        },
        {
          "segment_name": "Wafer",
          "value": 3272553500000.0,
          "unit": "USD",
          "period": "2025-12-31 (FY)",
          "concept": "xbrl_dimension",
          "is_annual": true
        }
      ],
      "total_revenue": null,
      "gross_profit": 2281294000000.0,
      "operating_income": null,
      "net_income": 1695124900000.0,
      "rd_expense": 246427200000.0,
      "sga_expense": null,
      "cogs": null,
      "interest_expense": null,
      "income_tax": null,
      "currency": "USD",
      "extraction_method": "xbrl",
      "confidence": 0.59,
      "notes": []
    },
    {
      "ticker": "TSM",
      "period": "FY2024",
      "is_annual": true,
      "fiscal_year": 2024,
      "fiscal_quarter": null,
      "segments": [
        {
          "segment_name": "Customer A [member]",
          "value": 976616700000.0,
          "unit": "USD",
          "period": "2024-12-31 (FY)",
          "concept": "xbrl_dimension",
          "is_annual": true
        },
        {
          "segment_name": "Customer C",
          "value": NaN,
          "unit": "USD",
          "period": "2024-12-31 (FY)",
          "concept": "xbrl_dimension",
          "is_annual": true
        }
      ],
      "total_revenue": null,
      "gross_profit": 1624353600000.0,
      "operating_income": null,
      "net_income": 1157523900000.0,
      "rd_expense": 204181800000.0,
      "sga_expense": null,
      "cogs": null,
      "interest_expense": null,
      "income_tax": null,
      "currency": "USD",
      "extraction_method": "xbrl",
      "confidence": 0.59,
      "notes": []
    },
    {
      "ticker": "TSM",
      "period": "FY2023",
      "is_annual": true,
      "fiscal_year": 2023,
      "fiscal_quarter": null,
      "segments": [
        {
          "segment_name": "Customer A [member]",
          "value": 787703300000.0,
          "unit": "USD",
          "period": "2023-12-31 (FY)",
          "concept": "xbrl_dimension",
          "is_annual": true
        }
      ],
      "total_revenue": null,
      "gross_profit": 1175110600000.0,
      "operating_income": null,
      "net_income": 851027700000.0,
      "rd_expense": 182370200000.0,
      "sga_expense": null,
      "cogs": null,
      "interest_expense": null,
      "income_tax": null,
      "currency": "USD",
      "extraction_method": "xbrl",
      "confidence": 0.59,
      "notes": []
    },
    {
      "ticker": "TSM",
      "period": "FY2022",
      "is_annual": true,
      "fiscal_year": 2022,
      "fiscal_quarter": null,
      "segments": [
        {
          "segment_name": "Customer A [member]",
          "value": NaN,
          "unit": "USD",
          "period": "2022-12-31 (FY)",
          "concept": "xbrl_dimension",
          "is_annual": true
        },
        {
          "segment_name": "Customer C",
          "value": NaN,
          "unit": "USD",
          "period": "2022-12-31 (FY)",
          "concept": "xbrl_dimension",
          "is_annual": true
        }
      ],
      "total_revenue": null,
      "gross_profit": 1348354800000.0,
      "operating_income": null,
      "net_income": 993294700000.0,
      "rd_expense": 163262200000.0,
      "sga_expense": null,
      "cogs": null,
      "interest_expense": null,
      "income_tax": null,
      "currency": "USD",
      "extraction_method": "xbrl",
      "confidence": 0.59,
      "notes": []
    }
  ],
  "quarterly_periods": [
    {
      "ticker": "TSM",
      "period": "2026Q2",
      "is_annual": false,
      "fiscal_year": 2026,
      "fiscal_quarter": 2,
      "segments": [],
      "total_revenue": null,
      "gross_profit": null,
      "operating_income": null,
      "net_income": null,
      "rd_expense": null,
      "sga_expense": null,
      "cogs": null,
      "interest_expense": null,
      "income_tax": null,
      "currency": "USD",
      "extraction_method": "edgar",
      "confidence": 0.0,
      "notes": []
    },
    {
      "ticker": "TSM",
      "period": "2026Q1",
      "is_annual": false,
      "fiscal_year": 2026,
      "fiscal_quarter": 1,
      "segments": [],
      "total_revenue": null,
      "gross_profit": null,
      "operating_income": null,
      "net_income": null,
      "rd_expense": null,
      "sga_expense": null,
      "cogs": null,
      "interest_expense": null,
      "income_tax": null,
      "currency": "USD",
      "extraction_method": "edgar",
      "confidence": 0.0,
      "notes": []
    },
    {
      "ticker": "TSM",
      "period": "2026Q1",
      "is_annual": false,
      "fiscal_year": 2026,
      "fiscal_quarter": 1,
      "segments": [],
      "total_revenue": null,
      "gross_profit": null,
      "operating_income": null,
      "net_income": null,
      "rd_expense": null,
      "sga_expense": null,
      "cogs": null,
      "interest_expense": null,
      "income_tax": null,
      "currency": "USD",
      "extraction_method": "edgar",
      "confidence": 0.0,
      "notes": []
    },
    {
      "ticker": "TSM",
      "period": "2026Q1",
      "is_annual": false,
      "fiscal_year": 2026,
      "fiscal_quarter": 1,
      "segments": [],
      "total_revenue": null,
      "gross_profit": null,
      "operating_income": null,
      "net_income": null,
      "rd_expense": null,
      "sga_expense": null,
      "cogs": null,
      "interest_expense": null,
      "income_tax": null,
      "currency": "USD",
      "extraction_method": "edgar",
      "confidence": 0.0,
      "notes": []
    },
    {
      "ticker": "TSM",
      "period": "2026Q1",
      "is_annual": false,
      "fiscal_year": 2026,
      "fiscal_quarter": 1,
      "segments": [],
      "total_revenue": null,
      "gross_profit": null,
      "operating_income": null,
      "net_income": null,
      "rd_expense": null,
      "sga_expense": null,
      "cogs": null,
      "interest_expense": null,
      "income_tax": null,
      "currency": "USD",
      "extraction_method": "edgar",
      "confidence": 0.0,
      "notes": []
    },
    {
      "ticker": "TSM",
      "period": "2026Q1",
      "is_annual": false,
      "fiscal_year": 2026,
      "fiscal_quarter": 1,
      "segments": [],
      "total_revenue": null,
      "gross_profit": null,
      "operating_income": null,
      "net_income": null,
      "rd_expense": null,
      "sga_expense": null,
      "cogs": null,
      "interest_expense": null,
      "income_tax": null,
      "currency": "USD",
      "extraction_method": "edgar",
      "confidence": 0.0,
      "notes": []
    },
    {
      "ticker": "TSM",
      "period": "2026Q1",
      "is_annual": false,
      "fiscal_year": 2026,
      "fiscal_quarter": 1,
      "segments": [],
      "total_revenue": null,
      "gross_profit": null,
      "operating_income": null,
      "net_income": null,
      "rd_expense": null,
      "sga_expense": null,
      "cogs": null,
      "interest_expense": null,
      "income_tax": null,
      "currency": "USD",
      "extraction_method": "edgar",
      "confidence": 0.0,
      "notes": []
    },
    {
      "ticker": "TSM",
      "period": "2026Q1",
      "is_annual": false,
      "fiscal_year": 2026,
      "fiscal_quarter": 1,
      "segments": [],
      "total_revenue": null,
      "gross_profit": null,
      "operating_income": null,
      "net_income": null,
      "rd_expense": null,
      "sga_expense": null,
      "cogs": null,
      "interest_expense": null,
      "income_tax": null,
      "currency": "USD",
      "extraction_method": "edgar",
      "confidence": 0.0,
      "notes": []
    },
    {
      "ticker": "TSM",
      "period": "2026Q1",
      "is_annual": false,
      "fiscal_year": 2026,
      "fiscal_quarter": 1,
      "segments": [],
      "total_revenue": null,
      "gross_profit": null,
      "operating_income": null,
      "net_income": null,
      "rd_expense": null,
      "sga_expense": null,
      "cogs": null,
      "interest_expense": null,
      "income_tax": null,
      "currency": "USD",
      "extraction_method": "edgar",
      "confidence": 0.0,
      "notes": []
    },
    {
      "ticker": "TSM",
      "period": "2026Q1",
      "is_annual": false,
      "fiscal_year": 2026,
      "fiscal_quarter": 1,
      "segments": [],
      "total_revenue": null,
      "gross_profit": null,
      "operating_income": null,
      "net_income": null,
      "rd_expense": null,
      "sga_expense": null,
      "cogs": null,
      "interest_expense": null,
      "income_tax": null,
      "currency": "USD",
      "extraction_method": "edgar",
      "confidence": 0.0,
      "notes": []
    },
    {
      "ticker": "TSM",
      "period": "2026Q1",
      "is_annual": false,
      "fiscal_year": 2026,
      "fiscal_quarter": 1,
      "segments": [],
      "total_revenue": null,
      "gross_profit": null,
      "operating_income": null,
      "net_income": null,
      "rd_expense": null,
      "sga_expense": null,
      "cogs": null,
      "interest_expense": null,
      "income_tax": null,
      "currency": "USD",
      "extraction_method": "edgar",
      "confidence": 0.0,
      "notes": []
    },
    {
      "ticker": "TSM",
      "period": "2026Q1",
      "is_annual": false,
      "fiscal_year": 2026,
      "fiscal_quarter": 1,
      "segments": [],
      "total_revenue": null,
      "gross_profit": null,
      "operating_income": null,
      "net_income": null,
      "rd_expense": null,
      "sga_expense": null,
      "cogs": null,
      "interest_expense": null,
      "income_tax": null,
      "currency": "USD",
      "extraction_method": "edgar",
      "confidence": 0.0,
      "notes": []
    },
    {
      "ticker": "TSM",
      "period": "2026Q1",
      "is_annual": false,
      "fiscal_year": 2026,
      "fiscal_quarter": 1,
      "segments": [],
      "total_revenue": null,
      "gross_profit": null,
      "operating_income": null,
      "net_income": null,
      "rd_expense": null,
      "sga_expense": null,
      "cogs": null,
      "interest_expense": null,
      "income_tax": null,
      "currency": "USD",
      "extraction_method": "edgar",
      "confidence": 0.0,
      "notes": []
    },
    {
      "ticker": "TSM",
      "period": "2025Q4",
      "is_annual": false,
      "fiscal_year": 2025,
      "fiscal_quarter": 4,
      "segments": [],
      "total_revenue": null,
      "gross_profit": null,
      "operating_income": null,
      "net_income": null,
      "rd_expense": null,
      "sga_expense": null,
      "cogs": null,
      "interest_expense": null,
      "income_tax": null,
      "currency": "USD",
      "extraction_method": "edgar",
      "confidence": 0.0,
      "notes": []
    },
    {
      "ticker": "TSM",
      "period": "2025Q4",
      "is_annual": false,
      "fiscal_year": 2025,
      "fiscal_quarter": 4,
      "segments": [],
      "total_revenue": null,
      "gross_profit": null,
      "operating_income": null,
      "net_income": null,
      "rd_expense": null,
      "sga_expense": null,
      "cogs": null,
      "interest_expense": null,
      "income_tax": null,
      "currency": "USD",
      "extraction_method": "edgar",
      "confidence": 0.0,
      "notes": []
    },
    {
      "ticker": "TSM",
      "period": "2025Q4",
      "is_annual": false,
      "fiscal_year": 2025,
      "fiscal_quarter": 4,
      "segments": [],
      "total_revenue": null,
      "gross_profit": null,
      "operating_income": null,
      "net_income": null,
      "rd_expense": null,
      "sga_expense": null,
      "cogs": null,
      "interest_expense": null,
      "income_tax": null,
      "currency": "USD",
      "extraction_method": "edgar",
      "confidence": 0.0,
      "notes": []
    },
    {
      "ticker": "TSM",
      "period": "2025Q4",
      "is_annual": false,
      "fiscal_year": 2025,
      "fiscal_quarter": 4,
      "segments": [],
      "total_revenue": null,
      "gross_profit": null,
      "operating_income": null,
      "net_income": null,
      "rd_expense": null,
      "sga_expense": null,
      "cogs": null,
      "interest_expense": null,
      "income_tax": null,
      "currency": "USD",
      "extraction_method": "edgar",
      "confidence": 0.0,
      "notes": []
    },
    {
      "ticker": "TSM",
      "period": "2025Q4",
      "is_annual": false,
      "fiscal_year": 2025,
      "fiscal_quarter": 4,
      "segments": [],
      "total_revenue": null,
      "gross_profit": null,
      "operating_income": null,
      "net_income": null,
      "rd_expense": null,
      "sga_expense": null,
      "cogs": null,
      "interest_expense": null,
      "income_tax": null,
      "currency": "USD",
      "extraction_method": "edgar",
      "confidence": 0.0,
      "notes": []
    },
    {
      "ticker": "TSM",
      "period": "2025Q4",
      "is_annual": false,
      "fiscal_year": 2025,
      "fiscal_quarter": 4,
      "segments": [],
      "total_revenue": null,
      "gross_profit": null,
      "operating_income": null,
      "net_income": null,
      "rd_expense": null,
      "sga_expense": null,
      "cogs": null,
      "interest_expense": null,
      "income_tax": null,
      "currency": "USD",
      "extraction_method": "edgar",
      "confidence": 0.0,
      "notes": []
    },
    {
      "ticker": "TSM",
      "period": "2025Q4",
      "is_annual": false,
      "fiscal_year": 2025,
      "fiscal_quarter": 4,
      "segments": [],
      "total_revenue": null,
      "gross_profit": null,
      "operating_income": null,
      "net_income": null,
      "rd_expense": null,
      "sga_expense": null,
      "cogs": null,
      "interest_expense": null,
      "income_tax": null,
      "currency": "USD",
      "extraction_method": "edgar",
      "confidence": 0.0,
      "notes": []
    },
    {
      "ticker": "TSM",
      "period": "2025Q4",
      "is_annual": false,
      "fiscal_year": 2025,
      "fiscal_quarter": 4,
      "segments": [],
      "total_revenue": null,
      "gross_profit": null,
      "operating_income": null,
      "net_income": null,
      "rd_expense": null,
      "sga_expense": null,
      "cogs": null,
      "interest_expense": null,
      "income_tax": null,
      "currency": "USD",
      "extraction_method": "edgar",
      "confidence": 0.0,
      "notes": []
    },
    {
      "ticker": "TSM",
      "period": "2025Q4",
      "is_annual": false,
      "fiscal_year": 2025,
      "fiscal_quarter": 4,
      "segments": [],
      "total_revenue": null,
      "gross_profit": null,
      "operating_income": null,
      "net_income": null,
      "rd_expense": null,
      "sga_expense": null,
      "cogs": null,
      "interest_expense": null,
      "income_tax": null,
      "currency": "USD",
      "extraction_method": "edgar",
      "confidence": 0.0,
      "notes": []
    },
    {
      "ticker": "TSM",
      "period": "2025Q4",
      "is_annual": false,
      "fiscal_year": 2025,
      "fiscal_quarter": 4,
      "segments": [],
      "total_revenue": null,
      "gross_profit": null,
      "operating_income": null,
      "net_income": null,
      "rd_expense": null,
      "sga_expense": null,
      "cogs": null,
      "interest_expense": null,
      "income_tax": null,
      "currency": "USD",
      "extraction_method": "edgar",
      "confidence": 0.0,
      "notes": []
    },
    {
      "ticker": "TSM",
      "period": "2025Q4",
      "is_annual": false,
      "fiscal_year": 2025,
      "fiscal_quarter": 4,
      "segments": [],
      "total_revenue": null,
      "gross_profit": null,
      "operating_income": null,
      "net_income": null,
      "rd_expense": null,
      "sga_expense": null,
      "cogs": null,
      "interest_expense": null,
      "income_tax": null,
      "currency": "USD",
      "extraction_method": "edgar",
      "confidence": 0.0,
      "notes": []
    },
    {
      "ticker": "TSM",
      "period": "2025Q4",
      "is_annual": false,
      "fiscal_year": 2025,
      "fiscal_quarter": 4,
      "segments": [],
      "total_revenue": null,
      "gross_profit": null,
      "operating_income": null,
      "net_income": null,
      "rd_expense": null,
      "sga_expense": null,
      "cogs": null,
      "interest_expense": null,
      "income_tax": null,
      "currency": "USD",
      "extraction_method": "edgar",
      "confidence": 0.0,
      "notes": []
    },
    {
      "ticker": "TSM",
      "period": "2025Q4",
      "is_annual": false,
      "fiscal_year": 2025,
      "fiscal_quarter": 4,
      "segments": [],
      "total_revenue": null,
      "gross_profit": null,
      "operating_income": null,
      "net_income": null,
      "rd_expense": null,
      "sga_expense": null,
      "cogs": null,
      "interest_expense": null,
      "income_tax": null,
      "currency": "USD",
      "extraction_method": "edgar",
      "confidence": 0.0,
      "notes": []
    },
    {
      "ticker": "TSM",
      "period": "2025Q4",
      "is_annual": false,
      "fiscal_year": 2025,
      "fiscal_quarter": 4,
      "segments": [],
      "total_revenue": null,
      "gross_profit": null,
      "operating_income": null,
      "net_income": null,
      "rd_expense": null,
      "sga_expense": null,
      "cogs": null,
      "interest_expense": null,
      "income_tax": null,
      "currency": "USD",
      "extraction_method": "edgar",
      "confidence": 0.0,
      "notes": []
    },
    {
      "ticker": "TSM",
      "period": "2025Q3",
      "is_annual": false,
      "fiscal_year": 2025,
      "fiscal_quarter": 3,
      "segments": [],
      "total_revenue": null,
      "gross_profit": null,
      "operating_income": null,
      "net_income": null,
      "rd_expense": null,
      "sga_expense": null,
      "cogs": null,
      "interest_expense": null,
      "income_tax": null,
      "currency": "USD",
      "extraction_method": "edgar",
      "confidence": 0.0,
      "notes": []
    },
    {
      "ticker": "TSM",
      "period": "2025Q3",
      "is_annual": false,
      "fiscal_year": 2025,
      "fiscal_quarter": 3,
      "segments": [],
      "total_revenue": null,
      "gross_profit": null,
      "operating_income": null,
      "net_income": null,
      "rd_expense": null,
      "sga_expense": null,
      "cogs": null,
      "interest_expense": null,
      "income_tax": null,
      "currency": "USD",
      "extraction_method": "edgar",
      "confidence": 0.0,
      "notes": []
    },
    {
      "ticker": "TSM",
      "period": "2025Q3",
      "is_annual": false,
      "fiscal_year": 2025,
      "fiscal_quarter": 3,
      "segments": [],
      "total_revenue": null,
      "gross_profit": null,
      "operating_income": null,
      "net_income": null,
      "rd_expense": null,
      "sga_expense": null,
      "cogs": null,
      "interest_expense": null,
      "income_tax": null,
      "currency": "USD",
      "extraction_method": "edgar",
      "confidence": 0.0,
      "notes": []
    },
    {
      "ticker": "TSM",
      "period": "2025Q3",
      "is_annual": false,
      "fiscal_year": 2025,
      "fiscal_quarter": 3,
      "segments": [],
      "total_revenue": null,
      "gross_profit": null,
      "operating_income": null,
      "net_income": null,
      "rd_expense": null,
      "sga_expense": null,
      "cogs": null,
      "interest_expense": null,
      "income_tax": null,
      "currency": "USD",
      "extraction_method": "edgar",
      "confidence": 0.0,
      "notes": []
    },
    {
      "ticker": "TSM",
      "period": "2025Q3",
      "is_annual": false,
      "fiscal_year": 2025,
      "fiscal_quarter": 3,
      "segments": [],
      "total_revenue": null,
      "gross_profit": null,
      "operating_income": null,
      "net_income": null,
      "rd_expense": null,
      "sga_expense": null,
      "cogs": null,
      "interest_expense": null,
      "income_tax": null,
      "currency": "USD",
      "extraction_method": "edgar",
      "confidence": 0.0,
      "notes": []
    },
    {
      "ticker": "TSM",
      "period": "2025Q3",
      "is_annual": false,
      "fiscal_year": 2025,
      "fiscal_quarter": 3,
      "segments": [],
      "total_revenue": null,
      "gross_profit": null,
      "operating_income": null,
      "net_income": null,
      "rd_expense": null,
      "sga_expense": null,
      "cogs": null,
      "interest_expense": null,
      "income_tax": null,
      "currency": "USD",
      "extraction_method": "edgar",
      "confidence": 0.0,
      "notes": []
    },
    {
      "ticker": "TSM",
      "period": "2025Q3",
      "is_annual": false,
      "fiscal_year": 2025,
      "fiscal_quarter": 3,
      "segments": [],
      "total_revenue": null,
      "gross_profit": null,
      "operating_income": null,
      "net_income": null,
      "rd_expense": null,
      "sga_expense": null,
      "cogs": null,
      "interest_expense": null,
      "income_tax": null,
      "currency": "USD",
      "extraction_method": "edgar",
      "confidence": 0.0,
      "notes": []
    },
    {
      "ticker": "TSM",
      "period": "2025Q3",
      "is_annual": false,
      "fiscal_year": 2025,
      "fiscal_quarter": 3,
      "segments": [],
      "total_revenue": null,
      "gross_profit": null,
      "operating_income": null,
      "net_income": null,
      "rd_expense": null,
      "sga_expense": null,
      "cogs": null,
      "interest_expense": null,
      "income_tax": null,
      "currency": "USD",
      "extraction_method": "edgar",
      "confidence": 0.0,
      "notes": []
    },
    {
      "ticker": "TSM",
      "period": "2025Q3",
      "is_annual": false,
      "fiscal_year": 2025,
      "fiscal_quarter": 3,
      "segments": [],
      "total_revenue": null,
      "gross_profit": null,
      "operating_income": null,
      "net_income": null,
      "rd_expense": null,
      "sga_expense": null,
      "cogs": null,
      "interest_expense": null,
      "income_tax": null,
      "currency": "USD",
      "extraction_method": "edgar",
      "confidence": 0.0,
      "notes": []
    },
    {
      "ticker": "TSM",
      "period": "2025Q3",
      "is_annual": false,
      "fiscal_year": 2025,
      "fiscal_quarter": 3,
      "segments": [],
      "total_revenue": null,
      "gross_profit": null,
      "operating_income": null,
      "net_income": null,
      "rd_expense": null,
      "sga_expense": null,
      "cogs": null,
      "interest_expense": null,
      "income_tax": null,
      "currency": "USD",
      "extraction_method": "edgar",
      "confidence": 0.0,
      "notes": []
    },
    {
      "ticker": "TSM",
      "period": "2025Q3",
      "is_annual": false,
      "fiscal_year": 2025,
      "fiscal_quarter": 3,
      "segments": [],
      "total_revenue": null,
      "gross_profit": null,
      "operating_income": null,
      "net_income": null,
      "rd_expense": null,
      "sga_expense": null,
      "cogs": null,
      "interest_expense": null,
      "income_tax": null,
      "currency": "USD",
      "extraction_method": "edgar",
      "confidence": 0.0,
      "notes": []
    },
    {
      "ticker": "TSM",
      "period": "2025Q3",
      "is_annual": false,
      "fiscal_year": 2025,
      "fiscal_quarter": 3,
      "segments": [],
      "total_revenue": null,
      "gross_profit": null,
      "operating_income": null,
      "net_income": null,
      "rd_expense": null,
      "sga_expense": null,
      "cogs": null,
      "interest_expense": null,
      "income_tax": null,
      "currency": "USD",
      "extraction_method": "edgar",
      "confidence": 0.0,
      "notes": []
    },
    {
      "ticker": "TSM",
      "period": "2025Q3",
      "is_annual": false,
      "fiscal_year": 2025,
      "fiscal_quarter": 3,
      "segments": [],
      "total_revenue": null,
      "gross_profit": null,
      "operating_income": null,
      "net_income": null,
      "rd_expense": null,
      "sga_expense": null,
      "cogs": null,
      "interest_expense": null,
      "income_tax": null,
      "currency": "USD",
      "extraction_method": "edgar",
      "confidence": 0.0,
      "notes": []
    },
    {
      "ticker": "TSM",
      "period": "2025Q3",
      "is_annual": false,
      "fiscal_year": 2025,
      "fiscal_quarter": 3,
      "segments": [],
      "total_revenue": null,
      "gross_profit": null,
      "operating_income": null,
      "net_income": null,
      "rd_expense": null,
      "sga_expense": null,
      "cogs": null,
      "interest_expense": null,
      "income_tax": null,
      "currency": "USD",
      "extraction_method": "edgar",
      "confidence": 0.0,
      "notes": []
    },
    {
      "ticker": "TSM",
      "period": "2025Q3",
      "is_annual": false,
      "fiscal_year": 2025,
      "fiscal_quarter": 3,
      "segments": [],
      "total_revenue": null,
      "gross_profit": null,
      "operating_income": null,
      "net_income": null,
      "rd_expense": null,
      "sga_expense": null,
      "cogs": null,
      "interest_expense": null,
      "income_tax": null,
      "currency": "USD",
      "extraction_method": "edgar",
      "confidence": 0.0,
      "notes": []
    },
    {
      "ticker": "TSM",
      "period": "2025Q2",
      "is_annual": false,
      "fiscal_year": 2025,
      "fiscal_quarter": 2,
      "segments": [],
      "total_revenue": null,
      "gross_profit": null,
      "operating_income": null,
      "net_income": null,
      "rd_expense": null,
      "sga_expense": null,
      "cogs": null,
      "interest_expense": null,
      "income_tax": null,
      "currency": "USD",
      "extraction_method": "edgar",
      "confidence": 0.0,
      "notes": []
    },
    {
      "ticker": "TSM",
      "period": "2025Q2",
      "is_annual": false,
      "fiscal_year": 2025,
      "fiscal_quarter": 2,
      "segments": [],
      "total_revenue": null,
      "gross_profit": null,
      "operating_income": null,
      "net_income": null,
      "rd_expense": null,
      "sga_expense": null,
      "cogs": null,
      "interest_expense": null,
      "income_tax": null,
      "currency": "USD",
      "extraction_method": "edgar",
      "confidence": 0.0,
      "notes": []
    },
    {
      "ticker": "TSM",
      "period": "2025Q2",
      "is_annual": false,
      "fiscal_year": 2025,
      "fiscal_quarter": 2,
      "segments": [],
      "total_revenue": null,
      "gross_profit": null,
      "operating_income": null,
      "net_income": null,
      "rd_expense": null,
      "sga_expense": null,
      "cogs": null,
      "interest_expense": null,
      "income_tax": null,
      "currency": "USD",
      "extraction_method": "edgar",
      "confidence": 0.0,
      "notes": []
    },
    {
      "ticker": "TSM",
      "period": "2025Q2",
      "is_annual": false,
      "fiscal_year": 2025,
      "fiscal_quarter": 2,
      "segments": [],
      "total_revenue": null,
      "gross_profit": null,
      "operating_income": null,
      "net_income": null,
      "rd_expense": null,
      "sga_expense": null,
      "cogs": null,
      "interest_expense": null,
      "income_tax": null,
      "currency": "USD",
      "extraction_method": "edgar",
      "confidence": 0.0,
      "notes": []
    },
    {
      "ticker": "TSM",
      "period": "2025Q2",
      "is_annual": false,
      "fiscal_year": 2025,
      "fiscal_quarter": 2,
      "segments": [],
      "total_revenue": null,
      "gross_profit": null,
      "operating_income": null,
      "net_income": null,
      "rd_expense": null,
      "sga_expense": null,
      "cogs": null,
      "interest_expense": null,
      "income_tax": null,
      "currency": "USD",
      "extraction_method": "edgar",
      "confidence": 0.0,
      "notes": []
    },
    {
      "ticker": "TSM",
      "period": "2025Q2",
      "is_annual": false,
      "fiscal_year": 2025,
      "fiscal_quarter": 2,
      "segments": [],
      "total_revenue": null,
      "gross_profit": null,
      "operating_income": null,
      "net_income": null,
      "rd_expense": null,
      "sga_expense": null,
      "cogs": null,
      "interest_expense": null,
      "income_tax": null,
      "currency": "USD",
      "extraction_method": "edgar",
      "confidence": 0.0,
      "notes": []
    },
    {
      "ticker": "TSM",
      "period": "2025Q2",
      "is_annual": false,
      "fiscal_year": 2025,
      "fiscal_quarter": 2,
      "segments": [],
      "total_revenue": null,
      "gross_profit": null,
      "operating_income": null,
      "net_income": null,
      "rd_expense": null,
      "sga_expense": null,
      "cogs": null,
      "interest_expense": null,
      "income_tax": null,
      "currency": "USD",
      "extraction_method": "edgar",
      "confidence": 0.0,
      "notes": []
    },
    {
      "ticker": "TSM",
      "period": "2025Q2",
      "is_annual": false,
      "fiscal_year": 2025,
      "fiscal_quarter": 2,
      "segments": [],
      "total_revenue": null,
      "gross_profit": null,
      "operating_income": null,
      "net_income": null,
      "rd_expense": null,
      "sga_expense": null,
      "cogs": null,
      "interest_expense": null,
      "income_tax": null,
      "currency": "USD",
      "extraction_method": "edgar",
      "confidence": 0.0,
      "notes": []
    },
    {
      "ticker": "TSM",
      "period": "2025Q2",
      "is_annual": false,
      "fiscal_year": 2025,
      "fiscal_quarter": 2,
      "segments": [],
      "total_revenue": null,
      "gross_profit": null,
      "operating_income": null,
      "net_income": null,
      "rd_expense": null,
      "sga_expense": null,
      "cogs": null,
      "interest_expense": null,
      "income_tax": null,
      "currency": "USD",
      "extraction_method": "edgar",
      "confidence": 0.0,
      "notes": []
    },
    {
      "ticker": "TSM",
      "period": "2025Q2",
      "is_annual": false,
      "fiscal_year": 2025,
      "fiscal_quarter": 2,
      "segments": [],
      "total_revenue": null,
      "gross_profit": null,
      "operating_income": null,
      "net_income": null,
      "rd_expense": null,
      "sga_expense": null,
      "cogs": null,
      "interest_expense": null,
      "income_tax": null,
      "currency": "USD",
      "extraction_method": "edgar",
      "confidence": 0.0,
      "notes": []
    },
    {
      "ticker": "TSM",
      "period": "2025Q2",
      "is_annual": false,
      "fiscal_year": 2025,
      "fiscal_quarter": 2,
      "segments": [],
      "total_revenue": null,
      "gross_profit": null,
      "operating_income": null,
      "net_income": null,
      "rd_expense": null,
      "sga_expense": null,
      "cogs": null,
      "interest_expense": null,
      "income_tax": null,
      "currency": "USD",
      "extraction_method": "edgar",
      "confidence": 0.0,
      "notes": []
    },
    {
      "ticker": "TSM",
      "period": "2025Q2",
      "is_annual": false,
      "fiscal_year": 2025,
      "fiscal_quarter": 2,
      "segments": [],
      "total_revenue": null,
      "gross_profit": null,
      "operating_income": null,
      "net_income": null,
      "rd_expense": null,
      "sga_expense": null,
      "cogs": null,
      "interest_expense": null,
      "income_tax": null,
      "currency": "USD",
      "extraction_method": "edgar",
      "confidence": 0.0,
      "notes": []
    },
    {
      "ticker": "TSM",
      "period": "2025Q2",
      "is_annual": false,
      "fiscal_year": 2025,
      "fiscal_quarter": 2,
      "segments": [],
      "total_revenue": null,
      "gross_profit": null,
      "operating_income": null,
      "net_income": null,
      "rd_expense": null,
      "sga_expense": null,
      "cogs": null,
      "interest_expense": null,
      "income_tax": null,
      "currency": "USD",
      "extraction_method": "edgar",
      "confidence": 0.0,
      "notes": []
    },
    {
      "ticker": "TSM",
      "period": "2025Q2",
      "is_annual": false,
      "fiscal_year": 2025,
      "fiscal_quarter": 2,
      "segments": [],
      "total_revenue": null,
      "gross_profit": null,
      "operating_income": null,
      "net_income": null,
      "rd_expense": null,
      "sga_expense": null,
      "cogs": null,
      "interest_expense": null,
      "income_tax": null,
      "currency": "USD",
      "extraction_method": "edgar",
      "confidence": 0.0,
      "notes": []
    },
    {
      "ticker": "TSM",
      "period": "2025Q2",
      "is_annual": false,
      "fiscal_year": 2025,
      "fiscal_quarter": 2,
      "segments": [],
      "total_revenue": null,
      "gross_profit": null,
      "operating_income": null,
      "net_income": null,
      "rd_expense": null,
      "sga_expense": null,
      "cogs": null,
      "interest_expense": null,
      "income_tax": null,
      "currency": "USD",
      "extraction_method": "edgar",
      "confidence": 0.0,
      "notes": []
    },
    {
      "ticker": "TSM",
      "period": "2025Q2",
      "is_annual": false,
      "fiscal_year": 2025,
      "fiscal_quarter": 2,
      "segments": [],
      "total_revenue": null,
      "gross_profit": null,
      "operating_income": null,
      "net_income": null,
      "rd_expense": null,
      "sga_expense": null,
      "cogs": null,
      "interest_expense": null,
      "income_tax": null,
      "currency": "USD",
      "extraction_method": "edgar",
      "confidence": 0.0,
      "notes": []
    },
    {
      "ticker": "TSM",
      "period": "2025Q1",
      "is_annual": false,
      "fiscal_year": 2025,
      "fiscal_quarter": 1,
      "segments": [],
      "total_revenue": null,
      "gross_profit": null,
      "operating_income": null,
      "net_income": null,
      "rd_expense": null,
      "sga_expense": null,
      "cogs": null,
      "interest_expense": null,
      "income_tax": null,
      "currency": "USD",
      "extraction_method": "edgar",
      "confidence": 0.0,
      "notes": []
    },
    {
      "ticker": "TSM",
      "period": "2025Q1",
      "is_annual": false,
      "fiscal_year": 2025,
      "fiscal_quarter": 1,
      "segments": [],
      "total_revenue": null,
      "gross_profit": null,
      "operating_income": null,
      "net_income": null,
      "rd_expense": null,
      "sga_expense": null,
      "cogs": null,
      "interest_expense": null,
      "income_tax": null,
      "currency": "USD",
      "extraction_method": "edgar",
      "confidence": 0.0,
      "notes": []
    },
    {
      "ticker": "TSM",
      "period": "2025Q1",
      "is_annual": false,
      "fiscal_year": 2025,
      "fiscal_quarter": 1,
      "segments": [],
      "total_revenue": null,
      "gross_profit": null,
      "operating_income": null,
      "net_income": null,
      "rd_expense": null,
      "sga_expense": null,
      "cogs": null,
      "interest_expense": null,
      "income_tax": null,
      "currency": "USD",
      "extraction_method": "edgar",
      "confidence": 0.0,
      "notes": []
    },
    {
      "ticker": "TSM",
      "period": "2025Q1",
      "is_annual": false,
      "fiscal_year": 2025,
      "fiscal_quarter": 1,
      "segments": [],
      "total_revenue": null,
      "gross_profit": null,
      "operating_income": null,
      "net_income": null,
      "rd_expense": null,
      "sga_expense": null,
      "cogs": null,
      "interest_expense": null,
      "income_tax": null,
      "currency": "USD",
      "extraction_method": "edgar",
      "confidence": 0.0,
      "notes": []
    },
    {
      "ticker": "TSM",
      "period": "2025Q1",
      "is_annual": false,
      "fiscal_year": 2025,
      "fiscal_quarter": 1,
      "segments": [],
      "total_revenue": null,
      "gross_profit": null,
      "operating_income": null,
      "net_income": null,
      "rd_expense": null,
      "sga_expense": null,
      "cogs": null,
      "interest_expense": null,
      "income_tax": null,
      "currency": "USD",
      "extraction_method": "edgar",
      "confidence": 0.0,
      "notes": []
    },
    {
      "ticker": "TSM",
      "period": "2025Q1",
      "is_annual": false,
      "fiscal_year": 2025,
      "fiscal_quarter": 1,
      "segments": [],
      "total_revenue": null,
      "gross_profit": null,
      "operating_income": null,
      "net_income": null,
      "rd_expense": null,
      "sga_expense": null,
      "cogs": null,
      "interest_expense": null,
      "income_tax": null,
      "currency": "USD",
      "extraction_method": "edgar",
      "confidence": 0.0,
      "notes": []
    },
    {
      "ticker": "TSM",
      "period": "2025Q1",
      "is_annual": false,
      "fiscal_year": 2025,
      "fiscal_quarter": 1,
      "segments": [],
      "total_revenue": null,
      "gross_profit": null,
      "operating_income": null,
      "net_income": null,
      "rd_expense": null,
      "sga_expense": null,
      "cogs": null,
      "interest_expense": null,
      "income_tax": null,
      "currency": "USD",
      "extraction_method": "edgar",
      "confidence": 0.0,
      "notes": []
    },
    {
      "ticker": "TSM",
      "period": "2025Q1",
      "is_annual": false,
      "fiscal_year": 2025,
      "fiscal_quarter": 1,
      "segments": [],
      "total_revenue": null,
      "gross_profit": null,
      "operating_income": null,
      "net_income": null,
      "rd_expense": null,
      "sga_expense": null,
      "cogs": null,
      "interest_expense": null,
      "income_tax": null,
      "currency": "USD",
      "extraction_method": "edgar",
      "confidence": 0.0,
      "notes": []
    },
    {
      "ticker": "TSM",
      "period": "2025Q1",
      "is_annual": false,
      "fiscal_year": 2025,
      "fiscal_quarter": 1,
      "segments": [],
      "total_revenue": null,
      "gross_profit": null,
      "operating_income": null,
      "net_income": null,
      "rd_expense": null,
      "sga_expense": null,
      "cogs": null,
      "interest_expense": null,
      "income_tax": null,
      "currency": "USD",
      "extraction_method": "edgar",
      "confidence": 0.0,
      "notes": []
    },
    {
      "ticker": "TSM",
      "period": "2025Q1",
      "is_annual": false,
      "fiscal_year": 2025,
      "fiscal_quarter": 1,
      "segments": [],
      "total_revenue": null,
      "gross_profit": null,
      "operating_income": null,
      "net_income": null,
      "rd_expense": null,
      "sga_expense": null,
      "cogs": null,
      "interest_expense": null,
      "income_tax": null,
      "currency": "USD",
      "extraction_method": "edgar",
      "confidence": 0.0,
      "notes": []
    },
    {
      "ticker": "TSM",
      "period": "2025Q1",
      "is_annual": false,
      "fiscal_year": 2025,
      "fiscal_quarter": 1,
      "segments": [],
      "total_revenue": null,
      "gross_profit": null,
      "operating_income": null,
      "net_income": null,
      "rd_expense": null,
      "sga_expense": null,
      "cogs": null,
      "interest_expense": null,
      "income_tax": null,
      "currency": "USD",
      "extraction_method": "edgar",
      "confidence": 0.0,
      "notes": []
    },
    {
      "ticker": "TSM",
      "period": "2025Q1",
      "is_annual": false,
      "fiscal_year": 2025,
      "fiscal_quarter": 1,
      "segments": [],
      "total_revenue": null,
      "gross_profit": null,
      "operating_income": null,
      "net_income": null,
      "rd_expense": null,
      "sga_expense": null,
      "cogs": null,
      "interest_expense": null,
      "income_tax": null,
      "currency": "USD",
      "extraction_method": "edgar",
      "confidence": 0.0,
      "notes": []
    },
    {
      "ticker": "TSM",
      "period": "2025Q1",
      "is_annual": false,
      "fiscal_year": 2025,
      "fiscal_quarter": 1,
      "segments": [],
      "total_revenue": null,
      "gross_profit": null,
      "operating_income": null,
      "net_income": null,
      "rd_expense": null,
      "sga_expense": null,
      "cogs": null,
      "interest_expense": null,
      "income_tax": null,
      "currency": "USD",
      "extraction_method": "edgar",
      "confidence": 0.0,
      "notes": []
    },
    {
      "ticker": "TSM",
      "period": "2025Q1",
      "is_annual": false,
      "fiscal_year": 2025,
      "fiscal_quarter": 1,
      "segments": [],
      "total_revenue": null,
      "gross_profit": null,
      "operating_income": null,
      "net_income": null,
      "rd_expense": null,
      "sga_expense": null,
      "cogs": null,
      "interest_expense": null,
      "income_tax": null,
      "currency": "USD",
      "extraction_method": "edgar",
      "confidence": 0.0,
      "notes": []
    },
    {
      "ticker": "TSM",
      "period": "2024Q4",
      "is_annual": false,
      "fiscal_year": 2024,
      "fiscal_quarter": 4,
      "segments": [],
      "total_revenue": null,
      "gross_profit": null,
      "operating_income": null,
      "net_income": null,
      "rd_expense": null,
      "sga_expense": null,
      "cogs": null,
      "interest_expense": null,
      "income_tax": null,
      "currency": "USD",
      "extraction_method": "edgar",
      "confidence": 0.0,
      "notes": []
    },
    {
      "ticker": "TSM",
      "period": "2024Q4",
      "is_annual": false,
      "fiscal_year": 2024,
      "fiscal_quarter": 4,
      "segments": [],
      "total_revenue": null,
      "gross_profit": null,
      "operating_income": null,
      "net_income": null,
      "rd_expense": null,
      "sga_expense": null,
      "cogs": null,
      "interest_expense": null,
      "income_tax": null,
      "currency": "USD",
      "extraction_method": "edgar",
      "confidence": 0.0,
      "notes": []
    },
    {
      "ticker": "TSM",
      "period": "2024Q4",
      "is_annual": false,
      "fiscal_year": 2024,
      "fiscal_quarter": 4,
      "segments": [],
      "total_revenue": null,
      "gross_profit": null,
      "operating_income": null,
      "net_income": null,
      "rd_expense": null,
      "sga_expense": null,
      "cogs": null,
      "interest_expense": null,
      "income_tax": null,
      "currency": "USD",
      "extraction_method": "edgar",
      "confidence": 0.0,
      "notes": []
    },
    {
      "ticker": "TSM",
      "period": "2024Q4",
      "is_annual": false,
      "fiscal_year": 2024,
      "fiscal_quarter": 4,
      "segments": [],
      "total_revenue": null,
      "gross_profit": null,
      "operating_income": null,
      "net_income": null,
      "rd_expense": null,
      "sga_expense": null,
      "cogs": null,
      "interest_expense": null,
      "income_tax": null,
      "currency": "USD",
      "extraction_method": "edgar",
      "confidence": 0.0,
      "notes": []
    },
    {
      "ticker": "TSM",
      "period": "2024Q4",
      "is_annual": false,
      "fiscal_year": 2024,
      "fiscal_quarter": 4,
      "segments": [],
      "total_revenue": null,
      "gross_profit": null,
      "operating_income": null,
      "net_income": null,
      "rd_expense": null,
      "sga_expense": null,
      "cogs": null,
      "interest_expense": null,
      "income_tax": null,
      "currency": "USD",
      "extraction_method": "edgar",
      "confidence": 0.0,
      "notes": []
    },
    {
      "ticker": "TSM",
      "period": "2024Q4",
      "is_annual": false,
      "fiscal_year": 2024,
      "fiscal_quarter": 4,
      "segments": [],
      "total_revenue": null,
      "gross_profit": null,
      "operating_income": null,
      "net_income": null,
      "rd_expense": null,
      "sga_expense": null,
      "cogs": null,
      "interest_expense": null,
      "income_tax": null,
      "currency": "USD",
      "extraction_method": "edgar",
      "confidence": 0.0,
      "notes": []
    },
    {
      "ticker": "TSM",
      "period": "2024Q4",
      "is_annual": false,
      "fiscal_year": 2024,
      "fiscal_quarter": 4,
      "segments": [],
      "total_revenue": null,
      "gross_profit": null,
      "operating_income": null,
      "net_income": null,
      "rd_expense": null,
      "sga_expense": null,
      "cogs": null,
      "interest_expense": null,
      "income_tax": null,
      "currency": "USD",
      "extraction_method": "edgar",
      "confidence": 0.0,
      "notes": []
    },
    {
      "ticker": "TSM",
      "period": "2024Q4",
      "is_annual": false,
      "fiscal_year": 2024,
      "fiscal_quarter": 4,
      "segments": [],
      "total_revenue": null,
      "gross_profit": null,
      "operating_income": null,
      "net_income": null,
      "rd_expense": null,
      "sga_expense": null,
      "cogs": null,
      "interest_expense": null,
      "income_tax": null,
      "currency": "USD",
      "extraction_method": "edgar",
      "confidence": 0.0,
      "notes": []
    },
    {
      "ticker": "TSM",
      "period": "2024Q4",
      "is_annual": false,
      "fiscal_year": 2024,
      "fiscal_quarter": 4,
      "segments": [],
      "total_revenue": null,
      "gross_profit": null,
      "operating_income": null,
      "net_income": null,
      "rd_expense": null,
      "sga_expense": null,
      "cogs": null,
      "interest_expense": null,
      "income_tax": null,
      "currency": "USD",
      "extraction_method": "edgar",
      "confidence": 0.0,
      "notes": []
    },
    {
      "ticker": "TSM",
      "period": "2024Q4",
      "is_annual": false,
      "fiscal_year": 2024,
      "fiscal_quarter": 4,
      "segments": [],
      "total_revenue": null,
      "gross_profit": null,
      "operating_income": null,
      "net_income": null,
      "rd_expense": null,
      "sga_expense": null,
      "cogs": null,
      "interest_expense": null,
      "income_tax": null,
      "currency": "USD",
      "extraction_method": "edgar",
      "confidence": 0.0,
      "notes": []
    },
    {
      "ticker": "TSM",
      "period": "2024Q4",
      "is_annual": false,
      "fiscal_year": 2024,
      "fiscal_quarter": 4,
      "segments": [],
      "total_revenue": null,
      "gross_profit": null,
      "operating_income": null,
      "net_income": null,
      "rd_expense": null,
      "sga_expense": null,
      "cogs": null,
      "interest_expense": null,
      "income_tax": null,
      "currency": "USD",
      "extraction_method": "edgar",
      "confidence": 0.0,
      "notes": []
    },
    {
      "ticker": "TSM",
      "period": "2024Q4",
      "is_annual": false,
      "fiscal_year": 2024,
      "fiscal_quarter": 4,
      "segments": [],
      "total_revenue": null,
      "gross_profit": null,
      "operating_income": null,
      "net_income": null,
      "rd_expense": null,
      "sga_expense": null,
      "cogs": null,
      "interest_expense": null,
      "income_tax": null,
      "currency": "USD",
      "extraction_method": "edgar",
      "confidence": 0.0,
      "notes": []
    },
    {
      "ticker": "TSM",
      "period": "2024Q4",
      "is_annual": false,
      "fiscal_year": 2024,
      "fiscal_quarter": 4,
      "segments": [],
      "total_revenue": null,
      "gross_profit": null,
      "operating_income": null,
      "net_income": null,
      "rd_expense": null,
      "sga_expense": null,
      "cogs": null,
      "interest_expense": null,
      "income_tax": null,
      "currency": "USD",
      "extraction_method": "edgar",
      "confidence": 0.0,
      "notes": []
    },
    {
      "ticker": "TSM",
      "period": "2024Q3",
      "is_annual": false,
      "fiscal_year": 2024,
      "fiscal_quarter": 3,
      "segments": [],
      "total_revenue": null,
      "gross_profit": null,
      "operating_income": null,
      "net_income": null,
      "rd_expense": null,
      "sga_expense": null,
      "cogs": null,
      "interest_expense": null,
      "income_tax": null,
      "currency": "USD",
      "extraction_method": "edgar",
      "confidence": 0.0,
      "notes": []
    },
    {
      "ticker": "TSM",
      "period": "2024Q3",
      "is_annual": false,
      "fiscal_year": 2024,
      "fiscal_quarter": 3,
      "segments": [],
      "total_revenue": null,
      "gross_profit": null,
      "operating_income": null,
      "net_income": null,
      "rd_expense": null,
      "sga_expense": null,
      "cogs": null,
      "interest_expense": null,
      "income_tax": null,
      "currency": "USD",
      "extraction_method": "edgar",
      "confidence": 0.0,
      "notes": []
    },
    {
      "ticker": "TSM",
      "period": "2024Q3",
      "is_annual": false,
      "fiscal_year": 2024,
      "fiscal_quarter": 3,
      "segments": [],
      "total_revenue": null,
      "gross_profit": null,
      "operating_income": null,
      "net_income": null,
      "rd_expense": null,
      "sga_expense": null,
      "cogs": null,
      "interest_expense": null,
      "income_tax": null,
      "currency": "USD",
      "extraction_method": "edgar",
      "confidence": 0.0,
      "notes": []
    },
    {
      "ticker": "TSM",
      "period": "2024Q3",
      "is_annual": false,
      "fiscal_year": 2024,
      "fiscal_quarter": 3,
      "segments": [],
      "total_revenue": null,
      "gross_profit": null,
      "operating_income": null,
      "net_income": null,
      "rd_expense": null,
      "sga_expense": null,
      "cogs": null,
      "interest_expense": null,
      "income_tax": null,
      "currency": "USD",
      "extraction_method": "edgar",
      "confidence": 0.0,
      "notes": []
    },
    {
      "ticker": "TSM",
      "period": "2024Q3",
      "is_annual": false,
      "fiscal_year": 2024,
      "fiscal_quarter": 3,
      "segments": [],
      "total_revenue": null,
      "gross_profit": null,
      "operating_income": null,
      "net_income": null,
      "rd_expense": null,
      "sga_expense": null,
      "cogs": null,
      "interest_expense": null,
      "income_tax": null,
      "currency": "USD",
      "extraction_method": "edgar",
      "confidence": 0.0,
      "notes": []
    },
    {
      "ticker": "TSM",
      "period": "2024Q3",
      "is_annual": false,
      "fiscal_year": 2024,
      "fiscal_quarter": 3,
      "segments": [],
      "total_revenue": null,
      "gross_profit": null,
      "operating_income": null,
      "net_income": null,
      "rd_expense": null,
      "sga_expense": null,
      "cogs": null,
      "interest_expense": null,
      "income_tax": null,
      "currency": "USD",
      "extraction_method": "edgar",
      "confidence": 0.0,
      "notes": []
    },
    {
      "ticker": "TSM",
      "period": "2024Q3",
      "is_annual": false,
      "fiscal_year": 2024,
      "fiscal_quarter": 3,
      "segments": [],
      "total_revenue": null,
      "gross_profit": null,
      "operating_income": null,
      "net_income": null,
      "rd_expense": null,
      "sga_expense": null,
      "cogs": null,
      "interest_expense": null,
      "income_tax": null,
      "currency": "USD",
      "extraction_method": "edgar",
      "confidence": 0.0,
      "notes": []
    },
    {
      "ticker": "TSM",
      "period": "2024Q3",
      "is_annual": false,
      "fiscal_year": 2024,
      "fiscal_quarter": 3,
      "segments": [],
      "total_revenue": null,
      "gross_profit": null,
      "operating_income": null,
      "net_income": null,
      "rd_expense": null,
      "sga_expense": null,
      "cogs": null,
      "interest_expense": null,
      "income_tax": null,
      "currency": "USD",
      "extraction_method": "edgar",
      "confidence": 0.0,
      "notes": []
    },
    {
      "ticker": "TSM",
      "period": "2024Q3",
      "is_annual": false,
      "fiscal_year": 2024,
      "fiscal_quarter": 3,
      "segments": [],
      "total_revenue": null,
      "gross_profit": null,
      "operating_income": null,
      "net_income": null,
      "rd_expense": null,
      "sga_expense": null,
      "cogs": null,
      "interest_expense": null,
      "income_tax": null,
      "currency": "USD",
      "extraction_method": "edgar",
      "confidence": 0.0,
      "notes": []
    },
    {
      "ticker": "TSM",
      "period": "2024Q3",
      "is_annual": false,
      "fiscal_year": 2024,
      "fiscal_quarter": 3,
      "segments": [],
      "total_revenue": null,
      "gross_profit": null,
      "operating_income": null,
      "net_income": null,
      "rd_expense": null,
      "sga_expense": null,
      "cogs": null,
      "interest_expense": null,
      "income_tax": null,
      "currency": "USD",
      "extraction_method": "edgar",
      "confidence": 0.0,
      "notes": []
    },
    {
      "ticker": "TSM",
      "period": "2024Q3",
      "is_annual": false,
      "fiscal_year": 2024,
      "fiscal_quarter": 3,
      "segments": [],
      "total_revenue": null,
      "gross_profit": null,
      "operating_income": null,
      "net_income": null,
      "rd_expense": null,
      "sga_expense": null,
      "cogs": null,
      "interest_expense": null,
      "income_tax": null,
      "currency": "USD",
      "extraction_method": "edgar",
      "confidence": 0.0,
      "notes": []
    },
    {
      "ticker": "TSM",
      "period": "2024Q3",
      "is_annual": false,
      "fiscal_year": 2024,
      "fiscal_quarter": 3,
      "segments": [],
      "total_revenue": null,
      "gross_profit": null,
      "operating_income": null,
      "net_income": null,
      "rd_expense": null,
      "sga_expense": null,
      "cogs": null,
      "interest_expense": null,
      "income_tax": null,
      "currency": "USD",
      "extraction_method": "edgar",
      "confidence": 0.0,
      "notes": []
    },
    {
      "ticker": "TSM",
      "period": "2024Q3",
      "is_annual": false,
      "fiscal_year": 2024,
      "fiscal_quarter": 3,
      "segments": [],
      "total_revenue": null,
      "gross_profit": null,
      "operating_income": null,
      "net_income": null,
      "rd_expense": null,
      "sga_expense": null,
      "cogs": null,
      "interest_expense": null,
      "income_tax": null,
      "currency": "USD",
      "extraction_method": "edgar",
      "confidence": 0.0,
      "notes": []
    },
    {
      "ticker": "TSM",
      "period": "2024Q3",
      "is_annual": false,
      "fiscal_year": 2024,
      "fiscal_quarter": 3,
      "segments": [],
      "total_revenue": null,
      "gross_profit": null,
      "operating_income": null,
      "net_income": null,
      "rd_expense": null,
      "sga_expense": null,
      "cogs": null,
      "interest_expense": null,
      "income_tax": null,
      "currency": "USD",
      "extraction_method": "edgar",
      "confidence": 0.0,
      "notes": []
    },
    {
      "ticker": "TSM",
      "period": "2024Q2",
      "is_annual": false,
      "fiscal_year": 2024,
      "fiscal_quarter": 2,
      "segments": [],
      "total_revenue": null,
      "gross_profit": null,
      "operating_income": null,
      "net_income": null,
      "rd_expense": null,
      "sga_expense": null,
      "cogs": null,
      "interest_expense": null,
      "income_tax": null,
      "currency": "USD",
      "extraction_method": "edgar",
      "confidence": 0.0,
      "notes": []
    },
    {
      "ticker": "TSM",
      "period": "2024Q2",
      "is_annual": false,
      "fiscal_year": 2024,
      "fiscal_quarter": 2,
      "segments": [],
      "total_revenue": null,
      "gross_profit": null,
      "operating_income": null,
      "net_income": null,
      "rd_expense": null,
      "sga_expense": null,
      "cogs": null,
      "interest_expense": null,
      "income_tax": null,
      "currency": "USD",
      "extraction_method": "edgar",
      "confidence": 0.0,
      "notes": []
    },
    {
      "ticker": "TSM",
      "period": "2024Q2",
      "is_annual": false,
      "fiscal_year": 2024,
      "fiscal_quarter": 2,
      "segments": [],
      "total_revenue": null,
      "gross_profit": null,
      "operating_income": null,
      "net_income": null,
      "rd_expense": null,
      "sga_expense": null,
      "cogs": null,
      "interest_expense": null,
      "income_tax": null,
      "currency": "USD",
      "extraction_method": "edgar",
      "confidence": 0.0,
      "notes": []
    },
    {
      "ticker": "TSM",
      "period": "2024Q2",
      "is_annual": false,
      "fiscal_year": 2024,
      "fiscal_quarter": 2,
      "segments": [],
      "total_revenue": null,
      "gross_profit": null,
      "operating_income": null,
      "net_income": null,
      "rd_expense": null,
      "sga_expense": null,
      "cogs": null,
      "interest_expense": null,
      "income_tax": null,
      "currency": "USD",
      "extraction_method": "edgar",
      "confidence": 0.0,
      "notes": []
    },
    {
      "ticker": "TSM",
      "period": "2024Q2",
      "is_annual": false,
      "fiscal_year": 2024,
      "fiscal_quarter": 2,
      "segments": [],
      "total_revenue": null,
      "gross_profit": null,
      "operating_income": null,
      "net_income": null,
      "rd_expense": null,
      "sga_expense": null,
      "cogs": null,
      "interest_expense": null,
      "income_tax": null,
      "currency": "USD",
      "extraction_method": "edgar",
      "confidence": 0.0,
      "notes": []
    },
    {
      "ticker": "TSM",
      "period": "2024Q2",
      "is_annual": false,
      "fiscal_year": 2024,
      "fiscal_quarter": 2,
      "segments": [],
      "total_revenue": null,
      "gross_profit": null,
      "operating_income": null,
      "net_income": null,
      "rd_expense": null,
      "sga_expense": null,
      "cogs": null,
      "interest_expense": null,
      "income_tax": null,
      "currency": "USD",
      "extraction_method": "edgar",
      "confidence": 0.0,
      "notes": []
    },
    {
      "ticker": "TSM",
      "period": "2024Q2",
      "is_annual": false,
      "fiscal_year": 2024,
      "fiscal_quarter": 2,
      "segments": [],
      "total_revenue": null,
      "gross_profit": null,
      "operating_income": null,
      "net_income": null,
      "rd_expense": null,
      "sga_expense": null,
      "cogs": null,
      "interest_expense": null,
      "income_tax": null,
      "currency": "USD",
      "extraction_method": "edgar",
      "confidence": 0.0,
      "notes": []
    },
    {
      "ticker": "TSM",
      "period": "2024Q2",
      "is_annual": false,
      "fiscal_year": 2024,
      "fiscal_quarter": 2,
      "segments": [],
      "total_revenue": null,
      "gross_profit": null,
      "operating_income": null,
      "net_income": null,
      "rd_expense": null,
      "sga_expense": null,
      "cogs": null,
      "interest_expense": null,
      "income_tax": null,
      "currency": "USD",
      "extraction_method": "edgar",
      "confidence": 0.0,
      "notes": []
    },
    {
      "ticker": "TSM",
      "period": "2024Q2",
      "is_annual": false,
      "fiscal_year": 2024,
      "fiscal_quarter": 2,
      "segments": [],
      "total_revenue": null,
      "gross_profit": null,
      "operating_income": null,
      "net_income": null,
      "rd_expense": null,
      "sga_expense": null,
      "cogs": null,
      "interest_expense": null,
      "income_tax": null,
      "currency": "USD",
      "extraction_method": "edgar",
      "confidence": 0.0,
      "notes": []
    },
    {
      "ticker": "TSM",
      "period": "2024Q2",
      "is_annual": false,
      "fiscal_year": 2024,
      "fiscal_quarter": 2,
      "segments": [],
      "total_revenue": null,
      "gross_profit": null,
      "operating_income": null,
      "net_income": null,
      "rd_expense": null,
      "sga_expense": null,
      "cogs": null,
      "interest_expense": null,
      "income_tax": null,
      "currency": "USD",
      "extraction_method": "edgar",
      "confidence": 0.0,
      "notes": []
    },
    {
      "ticker": "TSM",
      "period": "2024Q2",
      "is_annual": false,
      "fiscal_year": 2024,
      "fiscal_quarter": 2,
      "segments": [],
      "total_revenue": null,
      "gross_profit": null,
      "operating_income": null,
      "net_income": null,
      "rd_expense": null,
      "sga_expense": null,
      "cogs": null,
      "interest_expense": null,
      "income_tax": null,
      "currency": "USD",
      "extraction_method": "edgar",
      "confidence": 0.0,
      "notes": []
    },
    {
      "ticker": "TSM",
      "period": "2024Q2",
      "is_annual": false,
      "fiscal_year": 2024,
      "fiscal_quarter": 2,
      "segments": [],
      "total_revenue": null,
      "gross_profit": null,
      "operating_income": null,
      "net_income": null,
      "rd_expense": null,
      "sga_expense": null,
      "cogs": null,
      "interest_expense": null,
      "income_tax": null,
      "currency": "USD",
      "extraction_method": "edgar",
      "confidence": 0.0,
      "notes": []
    },
    {
      "ticker": "TSM",
      "period": "2024Q2",
      "is_annual": false,
      "fiscal_year": 2024,
      "fiscal_quarter": 2,
      "segments": [],
      "total_revenue": null,
      "gross_profit": null,
      "operating_income": null,
      "net_income": null,
      "rd_expense": null,
      "sga_expense": null,
      "cogs": null,
      "interest_expense": null,
      "income_tax": null,
      "currency": "USD",
      "extraction_method": "edgar",
      "confidence": 0.0,
      "notes": []
    },
    {
      "ticker": "TSM",
      "period": "2024Q2",
      "is_annual": false,
      "fiscal_year": 2024,
      "fiscal_quarter": 2,
      "segments": [],
      "total_revenue": null,
      "gross_profit": null,
      "operating_income": null,
      "net_income": null,
      "rd_expense": null,
      "sga_expense": null,
      "cogs": null,
      "interest_expense": null,
      "income_tax": null,
      "currency": "USD",
      "extraction_method": "edgar",
      "confidence": 0.0,
      "notes": []
    },
    {
      "ticker": "TSM",
      "period": "2024Q2",
      "is_annual": false,
      "fiscal_year": 2024,
      "fiscal_quarter": 2,
      "segments": [],
      "total_revenue": null,
      "gross_profit": null,
      "operating_income": null,
      "net_income": null,
      "rd_expense": null,
      "sga_expense": null,
      "cogs": null,
      "interest_expense": null,
      "income_tax": null,
      "currency": "USD",
      "extraction_method": "edgar",
      "confidence": 0.0,
      "notes": []
    },
    {
      "ticker": "TSM",
      "period": "2024Q2",
      "is_annual": false,
      "fiscal_year": 2024,
      "fiscal_quarter": 2,
      "segments": [],
      "total_revenue": null,
      "gross_profit": null,
      "operating_income": null,
      "net_income": null,
      "rd_expense": null,
      "sga_expense": null,
      "cogs": null,
      "interest_expense": null,
      "income_tax": null,
      "currency": "USD",
      "extraction_method": "edgar",
      "confidence": 0.0,
      "notes": []
    },
    {
      "ticker": "TSM",
      "period": "2024Q2",
      "is_annual": false,
      "fiscal_year": 2024,
      "fiscal_quarter": 2,
      "segments": [],
      "total_revenue": null,
      "gross_profit": null,
      "operating_income": null,
      "net_income": null,
      "rd_expense": null,
      "sga_expense": null,
      "cogs": null,
      "interest_expense": null,
      "income_tax": null,
      "currency": "USD",
      "extraction_method": "edgar",
      "confidence": 0.0,
      "notes": []
    },
    {
      "ticker": "TSM",
      "period": "2024Q2",
      "is_annual": false,
      "fiscal_year": 2024,
      "fiscal_quarter": 2,
      "segments": [],
      "total_revenue": null,
      "gross_profit": null,
      "operating_income": null,
      "net_income": null,
      "rd_expense": null,
      "sga_expense": null,
      "cogs": null,
      "interest_expense": null,
      "income_tax": null,
      "currency": "USD",
      "extraction_method": "edgar",
      "confidence": 0.0,
      "notes": []
    },
    {
      "ticker": "TSM",
      "period": "2024Q2",
      "is_annual": false,
      "fiscal_year": 2024,
      "fiscal_quarter": 2,
      "segments": [],
      "total_revenue": null,
      "gross_profit": null,
      "operating_income": null,
      "net_income": null,
      "rd_expense": null,
      "sga_expense": null,
      "cogs": null,
      "interest_expense": null,
      "income_tax": null,
      "currency": "USD",
      "extraction_method": "edgar",
      "confidence": 0.0,
      "notes": []
    },
    {
      "ticker": "TSM",
      "period": "2024Q2",
      "is_annual": false,
      "fiscal_year": 2024,
      "fiscal_quarter": 2,
      "segments": [],
      "total_revenue": null,
      "gross_profit": null,
      "operating_income": null,
      "net_income": null,
      "rd_expense": null,
      "sga_expense": null,
      "cogs": null,
      "interest_expense": null,
      "income_tax": null,
      "currency": "USD",
      "extraction_method": "edgar",
      "confidence": 0.0,
      "notes": []
    },
    {
      "ticker": "TSM",
      "period": "2024Q2",
      "is_annual": false,
      "fiscal_year": 2024,
      "fiscal_quarter": 2,
      "segments": [],
      "total_revenue": null,
      "gross_profit": null,
      "operating_income": null,
      "net_income": null,
      "rd_expense": null,
      "sga_expense": null,
      "cogs": null,
      "interest_expense": null,
      "income_tax": null,
      "currency": "USD",
      "extraction_method": "edgar",
      "confidence": 0.0,
      "notes": []
    },
    {
      "ticker": "TSM",
      "period": "2024Q1",
      "is_annual": false,
      "fiscal_year": 2024,
      "fiscal_quarter": 1,
      "segments": [],
      "total_revenue": null,
      "gross_profit": null,
      "operating_income": null,
      "net_income": null,
      "rd_expense": null,
      "sga_expense": null,
      "cogs": null,
      "interest_expense": null,
      "income_tax": null,
      "currency": "USD",
      "extraction_method": "edgar",
      "confidence": 0.0,
      "notes": []
    },
    {
      "ticker": "TSM",
      "period": "2024Q1",
      "is_annual": false,
      "fiscal_year": 2024,
      "fiscal_quarter": 1,
      "segments": [],
      "total_revenue": null,
      "gross_profit": null,
      "operating_income": null,
      "net_income": null,
      "rd_expense": null,
      "sga_expense": null,
      "cogs": null,
      "interest_expense": null,
      "income_tax": null,
      "currency": "USD",
      "extraction_method": "edgar",
      "confidence": 0.0,
      "notes": []
    },
    {
      "ticker": "TSM",
      "period": "2024Q1",
      "is_annual": false,
      "fiscal_year": 2024,
      "fiscal_quarter": 1,
      "segments": [],
      "total_revenue": null,
      "gross_profit": null,
      "operating_income": null,
      "net_income": null,
      "rd_expense": null,
      "sga_expense": null,
      "cogs": null,
      "interest_expense": null,
      "income_tax": null,
      "currency": "USD",
      "extraction_method": "edgar",
      "confidence": 0.0,
      "notes": []
    },
    {
      "ticker": "TSM",
      "period": "2024Q1",
      "is_annual": false,
      "fiscal_year": 2024,
      "fiscal_quarter": 1,
      "segments": [],
      "total_revenue": null,
      "gross_profit": null,
      "operating_income": null,
      "net_income": null,
      "rd_expense": null,
      "sga_expense": null,
      "cogs": null,
      "interest_expense": null,
      "income_tax": null,
      "currency": "USD",
      "extraction_method": "edgar",
      "confidence": 0.0,
      "notes": []
    },
    {
      "ticker": "TSM",
      "period": "2024Q1",
      "is_annual": false,
      "fiscal_year": 2024,
      "fiscal_quarter": 1,
      "segments": [],
      "total_revenue": null,
      "gross_profit": null,
      "operating_income": null,
      "net_income": null,
      "rd_expense": null,
      "sga_expense": null,
      "cogs": null,
      "interest_expense": null,
      "income_tax": null,
      "currency": "USD",
      "extraction_method": "edgar",
      "confidence": 0.0,
      "notes": []
    },
    {
      "ticker": "TSM",
      "period": "2024Q1",
      "is_annual": false,
      "fiscal_year": 2024,
      "fiscal_quarter": 1,
      "segments": [],
      "total_revenue": null,
      "gross_profit": null,
      "operating_income": null,
      "net_income": null,
      "rd_expense": null,
      "sga_expense": null,
      "cogs": null,
      "interest_expense": null,
      "income_tax": null,
      "currency": "USD",
      "extraction_method": "edgar",
      "confidence": 0.0,
      "notes": []
    },
    {
      "ticker": "TSM",
      "period": "2024Q1",
      "is_annual": false,
      "fiscal_year": 2024,
      "fiscal_quarter": 1,
      "segments": [],
      "total_revenue": null,
      "gross_profit": null,
      "operating_income": null,
      "net_income": null,
      "rd_expense": null,
      "sga_expense": null,
      "cogs": null,
      "interest_expense": null,
      "income_tax": null,
      "currency": "USD",
      "extraction_method": "edgar",
      "confidence": 0.0,
      "notes": []
    },
    {
      "ticker": "TSM",
      "period": "2024Q1",
      "is_annual": false,
      "fiscal_year": 2024,
      "fiscal_quarter": 1,
      "segments": [],
      "total_revenue": null,
      "gross_profit": null,
      "operating_income": null,
      "net_income": null,
      "rd_expense": null,
      "sga_expense": null,
      "cogs": null,
      "interest_expense": null,
      "income_tax": null,
      "currency": "USD",
      "extraction_method": "edgar",
      "confidence": 0.0,
      "notes": []
    },
    {
      "ticker": "TSM",
      "period": "2024Q1",
      "is_annual": false,
      "fiscal_year": 2024,
      "fiscal_quarter": 1,
      "segments": [],
      "total_revenue": null,
      "gross_profit": null,
      "operating_income": null,
      "net_income": null,
      "rd_expense": null,
      "sga_expense": null,
      "cogs": null,
      "interest_expense": null,
      "income_tax": null,
      "currency": "USD",
      "extraction_method": "edgar",
      "confidence": 0.0,
      "notes": []
    },
    {
      "ticker": "TSM",
      "period": "2024Q1",
      "is_annual": false,
      "fiscal_year": 2024,
      "fiscal_quarter": 1,
      "segments": [],
      "total_revenue": null,
      "gross_profit": null,
      "operating_income": null,
      "net_income": null,
      "rd_expense": null,
      "sga_expense": null,
      "cogs": null,
      "interest_expense": null,
      "income_tax": null,
      "currency": "USD",
      "extraction_method": "edgar",
      "confidence": 0.0,
      "notes": []
    },
    {
      "ticker": "TSM",
      "period": "2024Q1",
      "is_annual": false,
      "fiscal_year": 2024,
      "fiscal_quarter": 1,
      "segments": [],
      "total_revenue": null,
      "gross_profit": null,
      "operating_income": null,
      "net_income": null,
      "rd_expense": null,
      "sga_expense": null,
      "cogs": null,
      "interest_expense": null,
      "income_tax": null,
      "currency": "USD",
      "extraction_method": "edgar",
      "confidence": 0.0,
      "notes": []
    },
    {
      "ticker": "TSM",
      "period": "2024Q1",
      "is_annual": false,
      "fiscal_year": 2024,
      "fiscal_quarter": 1,
      "segments": [],
      "total_revenue": null,
      "gross_profit": null,
      "operating_income": null,
      "net_income": null,
      "rd_expense": null,
      "sga_expense": null,
      "cogs": null,
      "interest_expense": null,
      "income_tax": null,
      "currency": "USD",
      "extraction_method": "edgar",
      "confidence": 0.0,
      "notes": []
    },
    {
      "ticker": "TSM",
      "period": "2024Q1",
      "is_annual": false,
      "fiscal_year": 2024,
      "fiscal_quarter": 1,
      "segments": [],
      "total_revenue": null,
      "gross_profit": null,
      "operating_income": null,
      "net_income": null,
      "rd_expense": null,
      "sga_expense": null,
      "cogs": null,
      "interest_expense": null,
      "income_tax": null,
      "currency": "USD",
      "extraction_method": "edgar",
      "confidence": 0.0,
      "notes": []
    },
    {
      "ticker": "TSM",
      "period": "2024Q1",
      "is_annual": false,
      "fiscal_year": 2024,
      "fiscal_quarter": 1,
      "segments": [],
      "total_revenue": null,
      "gross_profit": null,
      "operating_income": null,
      "net_income": null,
      "rd_expense": null,
      "sga_expense": null,
      "cogs": null,
      "interest_expense": null,
      "income_tax": null,
      "currency": "USD",
      "extraction_method": "edgar",
      "confidence": 0.0,
      "notes": []
    },
    {
      "ticker": "TSM",
      "period": "2024Q1",
      "is_annual": false,
      "fiscal_year": 2024,
      "fiscal_quarter": 1,
      "segments": [],
      "total_revenue": null,
      "gross_profit": null,
      "operating_income": null,
      "net_income": null,
      "rd_expense": null,
      "sga_expense": null,
      "cogs": null,
      "interest_expense": null,
      "income_tax": null,
      "currency": "USD",
      "extraction_method": "edgar",
      "confidence": 0.0,
      "notes": []
    },
    {
      "ticker": "TSM",
      "period": "2024Q1",
      "is_annual": false,
      "fiscal_year": 2024,
      "fiscal_quarter": 1,
      "segments": [],
      "total_revenue": null,
      "gross_profit": null,
      "operating_income": null,
      "net_income": null,
      "rd_expense": null,
      "sga_expense": null,
      "cogs": null,
      "interest_expense": null,
      "income_tax": null,
      "currency": "USD",
      "extraction_method": "edgar",
      "confidence": 0.0,
      "notes": []
    },
    {
      "ticker": "TSM",
      "period": "2023Q4",
      "is_annual": false,
      "fiscal_year": 2023,
      "fiscal_quarter": 4,
      "segments": [],
      "total_revenue": null,
      "gross_profit": null,
      "operating_income": null,
      "net_income": null,
      "rd_expense": null,
      "sga_expense": null,
      "cogs": null,
      "interest_expense": null,
      "income_tax": null,
      "currency": "USD",
      "extraction_method": "edgar",
      "confidence": 0.0,
      "notes": []
    },
    {
      "ticker": "TSM",
      "period": "2023Q4",
      "is_annual": false,
      "fiscal_year": 2023,
      "fiscal_quarter": 4,
      "segments": [],
      "total_revenue": null,
      "gross_profit": null,
      "operating_income": null,
      "net_income": null,
      "rd_expense": null,
      "sga_expense": null,
      "cogs": null,
      "interest_expense": null,
      "income_tax": null,
      "currency": "USD",
      "extraction_method": "edgar",
      "confidence": 0.0,
      "notes": []
    },
    {
      "ticker": "TSM",
      "period": "2023Q4",
      "is_annual": false,
      "fiscal_year": 2023,
      "fiscal_quarter": 4,
      "segments": [],
      "total_revenue": null,
      "gross_profit": null,
      "operating_income": null,
      "net_income": null,
      "rd_expense": null,
      "sga_expense": null,
      "cogs": null,
      "interest_expense": null,
      "income_tax": null,
      "currency": "USD",
      "extraction_method": "edgar",
      "confidence": 0.0,
      "notes": []
    },
    {
      "ticker": "TSM",
      "period": "2023Q4",
      "is_annual": false,
      "fiscal_year": 2023,
      "fiscal_quarter": 4,
      "segments": [],
      "total_revenue": null,
      "gross_profit": null,
      "operating_income": null,
      "net_income": null,
      "rd_expense": null,
      "sga_expense": null,
      "cogs": null,
      "interest_expense": null,
      "income_tax": null,
      "currency": "USD",
      "extraction_method": "edgar",
      "confidence": 0.0,
      "notes": []
    },
    {
      "ticker": "TSM",
      "period": "2023Q4",
      "is_annual": false,
      "fiscal_year": 2023,
      "fiscal_quarter": 4,
      "segments": [],
      "total_revenue": null,
      "gross_profit": null,
      "operating_income": null,
      "net_income": null,
      "rd_expense": null,
      "sga_expense": null,
      "cogs": null,
      "interest_expense": null,
      "income_tax": null,
      "currency": "USD",
      "extraction_method": "edgar",
      "confidence": 0.0,
      "notes": []
    },
    {
      "ticker": "TSM",
      "period": "2023Q4",
      "is_annual": false,
      "fiscal_year": 2023,
      "fiscal_quarter": 4,
      "segments": [],
      "total_revenue": null,
      "gross_profit": null,
      "operating_income": null,
      "net_income": null,
      "rd_expense": null,
      "sga_expense": null,
      "cogs": null,
      "interest_expense": null,
      "income_tax": null,
      "currency": "USD",
      "extraction_method": "edgar",
      "confidence": 0.0,
      "notes": []
    },
    {
      "ticker": "TSM",
      "period": "2023Q4",
      "is_annual": false,
      "fiscal_year": 2023,
      "fiscal_quarter": 4,
      "segments": [],
      "total_revenue": null,
      "gross_profit": null,
      "operating_income": null,
      "net_income": null,
      "rd_expense": null,
      "sga_expense": null,
      "cogs": null,
      "interest_expense": null,
      "income_tax": null,
      "currency": "USD",
      "extraction_method": "edgar",
      "confidence": 0.0,
      "notes": []
    },
    {
      "ticker": "TSM",
      "period": "2023Q4",
      "is_annual": false,
      "fiscal_year": 2023,
      "fiscal_quarter": 4,
      "segments": [],
      "total_revenue": null,
      "gross_profit": null,
      "operating_income": null,
      "net_income": null,
      "rd_expense": null,
      "sga_expense": null,
      "cogs": null,
      "interest_expense": null,
      "income_tax": null,
      "currency": "USD",
      "extraction_method": "edgar",
      "confidence": 0.0,
      "notes": []
    },
    {
      "ticker": "TSM",
      "period": "2023Q4",
      "is_annual": false,
      "fiscal_year": 2023,
      "fiscal_quarter": 4,
      "segments": [],
      "total_revenue": null,
      "gross_profit": null,
      "operating_income": null,
      "net_income": null,
      "rd_expense": null,
      "sga_expense": null,
      "cogs": null,
      "interest_expense": null,
      "income_tax": null,
      "currency": "USD",
      "extraction_method": "edgar",
      "confidence": 0.0,
      "notes": []
    },
    {
      "ticker": "TSM",
      "period": "2023Q4",
      "is_annual": false,
      "fiscal_year": 2023,
      "fiscal_quarter": 4,
      "segments": [],
      "total_revenue": null,
      "gross_profit": null,
      "operating_income": null,
      "net_income": null,
      "rd_expense": null,
      "sga_expense": null,
      "cogs": null,
      "interest_expense": null,
      "income_tax": null,
      "currency": "USD",
      "extraction_method": "edgar",
      "confidence": 0.0,
      "notes": []
    },
    {
      "ticker": "TSM",
      "period": "2023Q4",
      "is_annual": false,
      "fiscal_year": 2023,
      "fiscal_quarter": 4,
      "segments": [],
      "total_revenue": null,
      "gross_profit": null,
      "operating_income": null,
      "net_income": null,
      "rd_expense": null,
      "sga_expense": null,
      "cogs": null,
      "interest_expense": null,
      "income_tax": null,
      "currency": "USD",
      "extraction_method": "edgar",
      "confidence": 0.0,
      "notes": []
    },
    {
      "ticker": "TSM",
      "period": "2023Q4",
      "is_annual": false,
      "fiscal_year": 2023,
      "fiscal_quarter": 4,
      "segments": [],
      "total_revenue": null,
      "gross_profit": null,
      "operating_income": null,
      "net_income": null,
      "rd_expense": null,
      "sga_expense": null,
      "cogs": null,
      "interest_expense": null,
      "income_tax": null,
      "currency": "USD",
      "extraction_method": "edgar",
      "confidence": 0.0,
      "notes": []
    },
    {
      "ticker": "TSM",
      "period": "2023Q4",
      "is_annual": false,
      "fiscal_year": 2023,
      "fiscal_quarter": 4,
      "segments": [],
      "total_revenue": null,
      "gross_profit": null,
      "operating_income": null,
      "net_income": null,
      "rd_expense": null,
      "sga_expense": null,
      "cogs": null,
      "interest_expense": null,
      "income_tax": null,
      "currency": "USD",
      "extraction_method": "edgar",
      "confidence": 0.0,
      "notes": []
    },
    {
      "ticker": "TSM",
      "period": "2023Q3",
      "is_annual": false,
      "fiscal_year": 2023,
      "fiscal_quarter": 3,
      "segments": [],
      "total_revenue": null,
      "gross_profit": null,
      "operating_income": null,
      "net_income": null,
      "rd_expense": null,
      "sga_expense": null,
      "cogs": null,
      "interest_expense": null,
      "income_tax": null,
      "currency": "USD",
      "extraction_method": "edgar",
      "confidence": 0.0,
      "notes": []
    },
    {
      "ticker": "TSM",
      "period": "2023Q3",
      "is_annual": false,
      "fiscal_year": 2023,
      "fiscal_quarter": 3,
      "segments": [],
      "total_revenue": null,
      "gross_profit": null,
      "operating_income": null,
      "net_income": null,
      "rd_expense": null,
      "sga_expense": null,
      "cogs": null,
      "interest_expense": null,
      "income_tax": null,
      "currency": "USD",
      "extraction_method": "edgar",
      "confidence": 0.0,
      "notes": []
    },
    {
      "ticker": "TSM",
      "period": "2023Q3",
      "is_annual": false,
      "fiscal_year": 2023,
      "fiscal_quarter": 3,
      "segments": [],
      "total_revenue": null,
      "gross_profit": null,
      "operating_income": null,
      "net_income": null,
      "rd_expense": null,
      "sga_expense": null,
      "cogs": null,
      "interest_expense": null,
      "income_tax": null,
      "currency": "USD",
      "extraction_method": "edgar",
      "confidence": 0.0,
      "notes": []
    },
    {
      "ticker": "TSM",
      "period": "2023Q3",
      "is_annual": false,
      "fiscal_year": 2023,
      "fiscal_quarter": 3,
      "segments": [],
      "total_revenue": null,
      "gross_profit": null,
      "operating_income": null,
      "net_income": null,
      "rd_expense": null,
      "sga_expense": null,
      "cogs": null,
      "interest_expense": null,
      "income_tax": null,
      "currency": "USD",
      "extraction_method": "edgar",
      "confidence": 0.0,
      "notes": []
    },
    {
      "ticker": "TSM",
      "period": "2023Q3",
      "is_annual": false,
      "fiscal_year": 2023,
      "fiscal_quarter": 3,
      "segments": [],
      "total_revenue": null,
      "gross_profit": null,
      "operating_income": null,
      "net_income": null,
      "rd_expense": null,
      "sga_expense": null,
      "cogs": null,
      "interest_expense": null,
      "income_tax": null,
      "currency": "USD",
      "extraction_method": "edgar",
      "confidence": 0.0,
      "notes": []
    },
    {
      "ticker": "TSM",
      "period": "2023Q3",
      "is_annual": false,
      "fiscal_year": 2023,
      "fiscal_quarter": 3,
      "segments": [],
      "total_revenue": null,
      "gross_profit": null,
      "operating_income": null,
      "net_income": null,
      "rd_expense": null,
      "sga_expense": null,
      "cogs": null,
      "interest_expense": null,
      "income_tax": null,
      "currency": "USD",
      "extraction_method": "edgar",
      "confidence": 0.0,
      "notes": []
    },
    {
      "ticker": "TSM",
      "period": "2023Q3",
      "is_annual": false,
      "fiscal_year": 2023,
      "fiscal_quarter": 3,
      "segments": [],
      "total_revenue": null,
      "gross_profit": null,
      "operating_income": null,
      "net_income": null,
      "rd_expense": null,
      "sga_expense": null,
      "cogs": null,
      "interest_expense": null,
      "income_tax": null,
      "currency": "USD",
      "extraction_method": "edgar",
      "confidence": 0.0,
      "notes": []
    },
    {
      "ticker": "TSM",
      "period": "2023Q3",
      "is_annual": false,
      "fiscal_year": 2023,
      "fiscal_quarter": 3,
      "segments": [],
      "total_revenue": null,
      "gross_profit": null,
      "operating_income": null,
      "net_income": null,
      "rd_expense": null,
      "sga_expense": null,
      "cogs": null,
      "interest_expense": null,
      "income_tax": null,
      "currency": "USD",
      "extraction_method": "edgar",
      "confidence": 0.0,
      "notes": []
    },
    {
      "ticker": "TSM",
      "period": "2023Q3",
      "is_annual": false,
      "fiscal_year": 2023,
      "fiscal_quarter": 3,
      "segments": [],
      "total_revenue": null,
      "gross_profit": null,
      "operating_income": null,
      "net_income": null,
      "rd_expense": null,
      "sga_expense": null,
      "cogs": null,
      "interest_expense": null,
      "income_tax": null,
      "currency": "USD",
      "extraction_method": "edgar",
      "confidence": 0.0,
      "notes": []
    },
    {
      "ticker": "TSM",
      "period": "2023Q3",
      "is_annual": false,
      "fiscal_year": 2023,
      "fiscal_quarter": 3,
      "segments": [],
      "total_revenue": null,
      "gross_profit": null,
      "operating_income": null,
      "net_income": null,
      "rd_expense": null,
      "sga_expense": null,
      "cogs": null,
      "interest_expense": null,
      "income_tax": null,
      "currency": "USD",
      "extraction_method": "edgar",
      "confidence": 0.0,
      "notes": []
    },
    {
      "ticker": "TSM",
      "period": "2023Q3",
      "is_annual": false,
      "fiscal_year": 2023,
      "fiscal_quarter": 3,
      "segments": [],
      "total_revenue": null,
      "gross_profit": null,
      "operating_income": null,
      "net_income": null,
      "rd_expense": null,
      "sga_expense": null,
      "cogs": null,
      "interest_expense": null,
      "income_tax": null,
      "currency": "USD",
      "extraction_method": "edgar",
      "confidence": 0.0,
      "notes": []
    },
    {
      "ticker": "TSM",
      "period": "2023Q3",
      "is_annual": false,
      "fiscal_year": 2023,
      "fiscal_quarter": 3,
      "segments": [],
      "total_revenue": null,
      "gross_profit": null,
      "operating_income": null,
      "net_income": null,
      "rd_expense": null,
      "sga_expense": null,
      "cogs": null,
      "interest_expense": null,
      "income_tax": null,
      "currency": "USD",
      "extraction_method": "edgar",
      "confidence": 0.0,
      "notes": []
    },
    {
      "ticker": "TSM",
      "period": "2023Q2",
      "is_annual": false,
      "fiscal_year": 2023,
      "fiscal_quarter": 2,
      "segments": [],
      "total_revenue": null,
      "gross_profit": null,
      "operating_income": null,
      "net_income": null,
      "rd_expense": null,
      "sga_expense": null,
      "cogs": null,
      "interest_expense": null,
      "income_tax": null,
      "currency": "USD",
      "extraction_method": "edgar",
      "confidence": 0.0,
      "notes": []
    },
    {
      "ticker": "TSM",
      "period": "2023Q2",
      "is_annual": false,
      "fiscal_year": 2023,
      "fiscal_quarter": 2,
      "segments": [],
      "total_revenue": null,
      "gross_profit": null,
      "operating_income": null,
      "net_income": null,
      "rd_expense": null,
      "sga_expense": null,
      "cogs": null,
      "interest_expense": null,
      "income_tax": null,
      "currency": "USD",
      "extraction_method": "edgar",
      "confidence": 0.0,
      "notes": []
    },
    {
      "ticker": "TSM",
      "period": "2023Q2",
      "is_annual": false,
      "fiscal_year": 2023,
      "fiscal_quarter": 2,
      "segments": [],
      "total_revenue": null,
      "gross_profit": null,
      "operating_income": null,
      "net_income": null,
      "rd_expense": null,
      "sga_expense": null,
      "cogs": null,
      "interest_expense": null,
      "income_tax": null,
      "currency": "USD",
      "extraction_method": "edgar",
      "confidence": 0.0,
      "notes": []
    },
    {
      "ticker": "TSM",
      "period": "2023Q2",
      "is_annual": false,
      "fiscal_year": 2023,
      "fiscal_quarter": 2,
      "segments": [],
      "total_revenue": null,
      "gross_profit": null,
      "operating_income": null,
      "net_income": null,
      "rd_expense": null,
      "sga_expense": null,
      "cogs": null,
      "interest_expense": null,
      "income_tax": null,
      "currency": "USD",
      "extraction_method": "edgar",
      "confidence": 0.0,
      "notes": []
    },
    {
      "ticker": "TSM",
      "period": "2023Q2",
      "is_annual": false,
      "fiscal_year": 2023,
      "fiscal_quarter": 2,
      "segments": [],
      "total_revenue": null,
      "gross_profit": null,
      "operating_income": null,
      "net_income": null,
      "rd_expense": null,
      "sga_expense": null,
      "cogs": null,
      "interest_expense": null,
      "income_tax": null,
      "currency": "USD",
      "extraction_method": "edgar",
      "confidence": 0.0,
      "notes": []
    },
    {
      "ticker": "TSM",
      "period": "2023Q2",
      "is_annual": false,
      "fiscal_year": 2023,
      "fiscal_quarter": 2,
      "segments": [],
      "total_revenue": null,
      "gross_profit": null,
      "operating_income": null,
      "net_income": null,
      "rd_expense": null,
      "sga_expense": null,
      "cogs": null,
      "interest_expense": null,
      "income_tax": null,
      "currency": "USD",
      "extraction_method": "edgar",
      "confidence": 0.0,
      "notes": []
    },
    {
      "ticker": "TSM",
      "period": "2023Q2",
      "is_annual": false,
      "fiscal_year": 2023,
      "fiscal_quarter": 2,
      "segments": [],
      "total_revenue": null,
      "gross_profit": null,
      "operating_income": null,
      "net_income": null,
      "rd_expense": null,
      "sga_expense": null,
      "cogs": null,
      "interest_expense": null,
      "income_tax": null,
      "currency": "USD",
      "extraction_method": "edgar",
      "confidence": 0.0,
      "notes": []
    },
    {
      "ticker": "TSM",
      "period": "2023Q2",
      "is_annual": false,
      "fiscal_year": 2023,
      "fiscal_quarter": 2,
      "segments": [],
      "total_revenue": null,
      "gross_profit": null,
      "operating_income": null,
      "net_income": null,
      "rd_expense": null,
      "sga_expense": null,
      "cogs": null,
      "interest_expense": null,
      "income_tax": null,
      "currency": "USD",
      "extraction_method": "edgar",
      "confidence": 0.0,
      "notes": []
    },
    {
      "ticker": "TSM",
      "period": "2023Q2",
      "is_annual": false,
      "fiscal_year": 2023,
      "fiscal_quarter": 2,
      "segments": [],
      "total_revenue": null,
      "gross_profit": null,
      "operating_income": null,
      "net_income": null,
      "rd_expense": null,
      "sga_expense": null,
      "cogs": null,
      "interest_expense": null,
      "income_tax": null,
      "currency": "USD",
      "extraction_method": "edgar",
      "confidence": 0.0,
      "notes": []
    },
    {
      "ticker": "TSM",
      "period": "2023Q2",
      "is_annual": false,
      "fiscal_year": 2023,
      "fiscal_quarter": 2,
      "segments": [],
      "total_revenue": null,
      "gross_profit": null,
      "operating_income": null,
      "net_income": null,
      "rd_expense": null,
      "sga_expense": null,
      "cogs": null,
      "interest_expense": null,
      "income_tax": null,
      "currency": "USD",
      "extraction_method": "edgar",
      "confidence": 0.0,
      "notes": []
    },
    {
      "ticker": "TSM",
      "period": "2023Q1",
      "is_annual": false,
      "fiscal_year": 2023,
      "fiscal_quarter": 1,
      "segments": [],
      "total_revenue": null,
      "gross_profit": null,
      "operating_income": null,
      "net_income": null,
      "rd_expense": null,
      "sga_expense": null,
      "cogs": null,
      "interest_expense": null,
      "income_tax": null,
      "currency": "USD",
      "extraction_method": "edgar",
      "confidence": 0.0,
      "notes": []
    },
    {
      "ticker": "TSM",
      "period": "2023Q1",
      "is_annual": false,
      "fiscal_year": 2023,
      "fiscal_quarter": 1,
      "segments": [],
      "total_revenue": null,
      "gross_profit": null,
      "operating_income": null,
      "net_income": null,
      "rd_expense": null,
      "sga_expense": null,
      "cogs": null,
      "interest_expense": null,
      "income_tax": null,
      "currency": "USD",
      "extraction_method": "edgar",
      "confidence": 0.0,
      "notes": []
    },
    {
      "ticker": "TSM",
      "period": "2023Q1",
      "is_annual": false,
      "fiscal_year": 2023,
      "fiscal_quarter": 1,
      "segments": [],
      "total_revenue": null,
      "gross_profit": null,
      "operating_income": null,
      "net_income": null,
      "rd_expense": null,
      "sga_expense": null,
      "cogs": null,
      "interest_expense": null,
      "income_tax": null,
      "currency": "USD",
      "extraction_method": "edgar",
      "confidence": 0.0,
      "notes": []
    },
    {
      "ticker": "TSM",
      "period": "2022Q4",
      "is_annual": false,
      "fiscal_year": 2022,
      "fiscal_quarter": 4,
      "segments": [],
      "total_revenue": null,
      "gross_profit": null,
      "operating_income": null,
      "net_income": null,
      "rd_expense": null,
      "sga_expense": null,
      "cogs": null,
      "interest_expense": null,
      "income_tax": null,
      "currency": "USD",
      "extraction_method": "edgar",
      "confidence": 0.0,
      "notes": []
    }
  ],
  "ttm_revenue": null,
  "ttm_operating_income": null,
  "ttm_net_income": null,
  "segment_trend": {
    "Customer A [member]": [
      {
        "period": "FY2022",
        "value": NaN,
        "is_annual": true
      },
      {
        "period": "FY2023",
        "value": 787703300000.0,
        "is_annual": true
      },
      {
        "period": "FY2024",
        "value": 976616700000.0,
        "is_annual": true
      }
    ],
    "Customer C": [
      {
        "period": "FY2022",
        "value": NaN,
        "is_annual": true
      },
      {
        "period": "FY2024",
        "value": NaN,
        "is_annual": true
      }
    ],
    "Others": [
      {
        "period": "FY2025",
        "value": 536500800000.0,
        "is_annual": true
      }
    ],
    "Wafer": [
      {
        "period": "FY2025",
        "value": 3272553500000.0,
        "is_annual": true
      }
    ]
  },
  "annual_count": 4,
  "quarterly_count": 175,
  "has_partial_data": false,
  "data_notes": []
}