{"timestamp": 1778494017.527663, "data": {"ticker": "GOOGL", "data_source": "both", "classification": "US_SEC", "sector": "standard", "filing_type": "10-K/10-Q", "cik": "0001652044", "confidence": 0.6, "notes": ["CIK via edgartools: 0001652044", "Submissions fetched for CIK 0001652044", "US SEC filer (forms found: {'10-K', '10-Q'})", "Yahoo Finance: sector='Communication Services', industry='Internet Content & Information'", "SIC 7370 → using as secondary signal only", "No strong sector signal → standard"]}}