{"timestamp": 1778848484.021875, "data": {"annual_income": {"2025-12-31": {"Tax Effect Of Unusual Items": 30219728891.932095, "Tax Rate For Calcs": 0.086389, "Normalized EBITDA": 96664037000000.0, "Total Unusual Items": 349809000000.0, "Total Unusual Items Excluding Goodwill": 349809000000.0, "Net Income From Continuing Operation Net Minority Interest": 44260956000000.0, "Reconciled Depreciation": 46926592000000.0, "Reconciled Cost Of Revenue": 202235513000000.0, "EBITDA": 97013846000000.0, "EBIT": 50087254000000.0, "Net Interest Income": 3987311000000.0, "Interest Expense": 605783000000.0, "Interest Income": 4593094000000.0, "Normalized Income": 43941366728891.93, "Net Income From Continuing And Discontinued Operation": 44260956000000.0, "Total Expenses": 290004887000000.0, "Total Operating Income As Reported": 43601051000000.0, "Diluted Average Shares": 6703158564.0, "Basic Average Shares": 6701128842.0, "Diluted EPS": 6603.0, "Basic EPS": 6605.0, "Net Income Common Stockholders": 44260956000000.0, "Net Income": 44260956000000.0, "Minority Interests": -945849000000.0, "Net Income Including Noncontrolling Interests": 45206805000000.0, "Net Income Continuous Operations": 45206805000000.0, "Tax Provision": 4274666000000.0, "Pretax Income": 49481471000000.0, "Other Non Operating Income Expenses": 721394000000.0, "Special Income Charges": -153184000000.0, "Other Special Charges": 153184000000.0, "Net Non Operating Interest Income Expense": 3987311000000.0, "Interest Expense Non Operating": 605783000000.0, "Interest Income Non Operating": 4593094000000.0, "Operating Income": 43601051000000.0, "Operating Expense": 87769374000000.0, "Depreciation And Amortization In Income Statement": 2553265000000.0, "Amortization": 813976000000.0, "Depreciation Income Statement": 1739289000000.0, "Research And Development": 37740392000000.0, "Selling General And Administration": 37849252000000.0, "Selling And Marketing Expense": 30228345000000.0, "General And Administrative Expense": 7620907000000.0, "Gross Profit": 131370425000000.0, "Cost Of Revenue": 202235513000000.0, "Total Revenue": 333605938000000.0, "Operating Revenue": 333605938000000.0}, "2024-12-31": {"Tax Effect Of Unusual Items": -7643351884.3752, "Tax Rate For Calcs": 0.082025, "Normalized EBITDA": 81157657000000.0, "Total Unusual Items": -93183000000.0, "Total Unusual Items Excluding Goodwill": -93183000000.0, "Net Income From Continuing Operation Net Minority Interest": 33621363000000.0, "Reconciled Depreciation": 42630822000000.0, "Reconciled Cost Of Revenue": 186562268000000.0, "EBITDA": 81064474000000.0, "EBIT": 38433652000000.0, "Net Interest Income": 3915210000000.0, "Interest Expense": 903918000000.0, "Interest Income": 4819128000000.0, "Normalized Income": 33706902648115.625, "Net Income From Continuing And Discontinued Operation": 33621363000000.0, "Total Expenses": 268144942000000.0, "Total Operating Income As Reported": 32725961000000.0, "Diluted Average Shares": 6792194545.0, "Basic Average Shares": 6792194545.0, "Diluted EPS": 4950.0, "Basic EPS": 4950.0, "Net Income Common Stockholders": 33621363000000.0, "Net Income": 33621363000000.0, "Minority Interests": -829988000000.0, "Net Income Including Noncontrolling Interests": 34451351000000.0, "Net Income Continuous Operations": 34451351000000.0, "Tax Provision": 3078383000000.0, "Pretax Income": 37529734000000.0, "Other Non Operating Income Expenses": 458747000000.0, "Special Income Charges": -258590000000.0, "Other Special Charges": 258590000000.0, "Net Non Operating Interest Income Expense": 3915210000000.0, "Interest Expense Non Operating": 903918000000.0, "Interest Income Non Operating": 4819128000000.0, "Operating Income": 32725961000000.0, "Operating Expense": 81582674000000.0, "Depreciation And Amortization In Income Statement": 2405725000000.0, "Amortization": 716646000000.0, "Depreciation Income Statement": 1689079000000.0, "Research And Development": 34998142000000.0, "Selling General And Administration": 35078235000000.0, "Selling And Marketing Expense": 28340823000000.0, "General And Administrative Expense": 6737412000000.0, "Gross Profit": 114308635000000.0, "Cost Of Revenue": 186562268000000.0, "Total Revenue": 300870903000000.0, "Operating Revenue": 300870903000000.0}, "2023-12-31": {"Tax Effect Of Unusual Items": -22864080000.0, "Tax Rate For Calcs": 0.24, "Normalized EBITDA": 50698344000000.0, "Total Unusual Items": -95267000000.0, "Total Unusual Items Excluding Goodwill": -95267000000.0, "Net Income From Continuing Operation Net Minority Interest": 14473401000000.0, "Reconciled Depreciation": 38666559000000.0, "Reconciled Cost Of Revenue": 180388580000000.0, "EBITDA": 50603077000000.0, "EBIT": 11936518000000.0, "Net Interest Income": 3427769000000.0, "Interest Expense": 930253000000.0, "Interest Income": 4358022000000.0, "Normalized Income": 14545803920000.0, "Net Income From Continuing And Discontinued Operation": 14473401000000.0, "Total Expenses": 252368518000000.0, "Total Operating Income As Reported": 6566976000000.0, "Diluted Average Shares": 6791835289.0, "Basic Average Shares": 6791835289.0, "Diluted EPS": 2131.0, "Basic EPS": 2131.0, "Net Income Common Stockholders": 14473401000000.0, "Net Income": 14473401000000.0, "Minority Interests": -1013699000000.0, "Net Income Including Noncontrolling Interests": 15487100000000.0, "Net Income Continuous Operations": 15487100000000.0, "Tax Provision": -4480835000000.0, "Pretax Income": 11006265000000.0, "Other Non Operating Income Expenses": 157431000000.0, "Special Income Charges": -224513000000.0, "Other Special Charges": 224513000000.0, "Net Non Operating Interest Income Expense": 3427769000000.0, "Interest Expense Non Operating": 930253000000.0, "Interest Income Non Operating": 4358022000000.0, "Operating Income": 6566976000000.0, "Operating Expense": 71979938000000.0, "Depreciation And Amortization In Income Statement": 2338121000000.0, "Amortization": 688786000000.0, "Depreciation Income Statement": 1649335000000.0, "Research And Development": 28339724000000.0, "Selling General And Administration": 32678162000000.0, "Selling And Marketing Expense": 26552163000000.0, "General And Administrative Expense": 6125999000000.0, "Gross Profit": 78546914000000.0, "Cost Of Revenue": 180388580000000.0, "Total Revenue": 258935494000000.0, "Operating Revenue": 258935494000000.0}, "2022-12-31": {"Tax Effect Of Unusual Items": -25405600000.0, "Tax Rate For Calcs": 0.275, "Normalized EBITDA": 86403532000000.0, "Total Unusual Items": -92384000000.0, "Total Unusual Items Excluding Goodwill": -92384000000.0, "Net Income From Continuing Operation Net Minority Interest": 54730018000000.0, "Reconciled Depreciation": 39107659000000.0, "Reconciled Cost Of Revenue": 190041770000000.0, "EBITDA": 86311148000000.0, "EBIT": 47203489000000.0, "Net Interest Income": 1957464000000.0, "Interest Expense": 763015000000.0, "Interest Income": 2720479000000.0, "Normalized Income": 54796996400000.0, "Net Income From Continuing And Discontinued Operation": 54730018000000.0, "Total Expenses": 258854730000000.0, "Total Operating Income As Reported": 43376630000000.0, "Diluted Average Shares": 6792853171.0, "Basic Average Shares": 6792853171.0, "Diluted EPS": 8057.0, "Basic EPS": 8057.0, "Net Income Common Stockholders": 54730018000000.0, "Net Income": 54730018000000.0, "Minority Interests": -924059000000.0, "Net Income Including Noncontrolling Interests": 55654077000000.0, "Net Income Continuous Operations": 55654077000000.0, "Tax Provision": -9213603000000.0, "Pretax Income": 46440474000000.0, "Other Non Operating Income Expenses": -34632000000.0, "Special Income Charges": -208074000000.0, "Other Special Charges": 208074000000.0, "Net Non Operating Interest Income Expense": 1957464000000.0, "Interest Expense Non Operating": 763015000000.0, "Interest Income Non Operating": 2720479000000.0, "Operating Income": 43376630000000.0, "Operating Expense": 68812960000000.0, "Depreciation And Amortization In Income Statement": 2239103000000.0, "Amortization": 664346000000.0, "Depreciation Income Statement": 1574757000000.0, "Research And Development": 24919198000000.0, "Selling General And Administration": 33560956000000.0, "Selling And Marketing Expense": 27567710000000.0, "General And Administrative Expense": 5993246000000.0, "Gross Profit": 112189590000000.0, "Cost Of Revenue": 190041770000000.0, "Total Revenue": 302231360000000.0, "Operating Revenue": 302231360000000.0}}, "quarterly_income": {"2025-12-31": {"Tax Effect Of Unusual Items": -3543055654.636775, "Tax Rate For Calcs": 0.065933, "Normalized EBITDA": 33479214000000.0, "Total Unusual Items": -53737000000.0, "Total Unusual Items Excluding Goodwill": -53737000000.0, "Net Income From Continuing Operation Net Minority Interest": 19292054000000.0, "Reconciled Depreciation": 12232032000000.0, "Reconciled Cost Of Revenue": 49586396000000.0, "EBITDA": 33425477000000.0, "EBIT": 21193445000000.0, "Net Interest Income": 965075000000.0, "Interest Expense": 165242000000.0, "Interest Income": 1130317000000.0, "Normalized Income": 19342247944345.363, "Net Income From Continuing And Discontinued Operation": 19292054000000.0, "Total Expenses": 73763711000000.0, "Total Operating Income As Reported": 20073660000000.0, "Diluted Average Shares": null, "Basic Average Shares": null, "Diluted EPS": null, "Basic EPS": null, "Net Income Common Stockholders": 19292054000000.0, "Net Income": 19292054000000.0, "Minority Interests": -349691000000.0, "Net Income Including Noncontrolling Interests": 19641745000000.0, "Net Income Continuous Operations": 19641745000000.0, "Tax Provision": 1386458000000.0, "Pretax Income": 21028203000000.0, "Other Non Operating Income Expenses": -38290000000.0, "Special Income Charges": -88952000000.0, "Other Special Charges": 88952000000.0, "Net Non Operating Interest Income Expense": 965075000000.0, "Total Other Finance Cost": null, "Interest Expense Non Operating": 165242000000.0, "Interest Income Non Operating": 1130317000000.0, "Operating Income": 20073660000000.0, "Operating Expense": 24177315000000.0, "Depreciation And Amortization In Income Statement": 676205000000.0, "Amortization": 224019000000.0, "Depreciation Income Statement": 452186000000.0, "Research And Development": 10864311000000.0, "Selling General And Administration": 9910391000000.0, "Selling And Marketing Expense": 7547604000000.0, "General And Administrative Expense": 2362787000000.0, "Gross Profit": 44250975000000.0, "Cost Of Revenue": 49586396000000.0, "Total Revenue": 93837371000000.0, "Operating Revenue": 93837371000000.0}, "2025-09-30": {"Tax Effect Of Unusual Items": -4903528927.959657, "Tax Rate For Calcs": 0.097435, "Normalized EBITDA": 25530861000000.0, "Total Unusual Items": -50326000000.0, "Total Unusual Items Excluding Goodwill": -50326000000.0, "Net Income From Continuing Operation Net Minority Interest": 12006461000000.0, "Reconciled Depreciation": 11819048000000.0, "Reconciled Cost Of Revenue": 52569620000000.0, "EBITDA": 25480535000000.0, "EBIT": 13661487000000.0, "Net Interest Income": 1056309000000.0, "Interest Expense": 115924000000.0, "Interest Income": 1172233000000.0, "Normalized Income": 12051883471072.041, "Net Income From Continuing And Discontinued Operation": 12006461000000.0, "Total Expenses": 73895685000000.0, "Total Operating Income As Reported": 12166062000000.0, "Diluted Average Shares": 5858733000.0, "Basic Average Shares": 5855461000.0, "Diluted EPS": 1801.0, "Basic EPS": 1802.0, "Net Income Common Stockholders": 12006461000000.0, "Net Income": 12006461000000.0, "Minority Interests": -219286000000.0, "Net Income Including Noncontrolling Interests": 12225747000000.0, "Net Income Continuous Operations": 12225747000000.0, "Tax Provision": 1319816000000.0, "Pretax Income": 13545563000000.0, "Other Non Operating Income Expenses": -110129000000.0, "Special Income Charges": -11996000000.0, "Other Special Charges": 11996000000.0, "Net Non Operating Interest Income Expense": 1056309000000.0, "Total Other Finance Cost": -1194454000000.0, "Interest Expense Non Operating": 115924000000.0, "Interest Income Non Operating": 1172233000000.0, "Operating Income": 12166062000000.0, "Operating Expense": 21326065000000.0, "Depreciation And Amortization In Income Statement": 627665000000.0, "Amortization": 203264000000.0, "Depreciation Income Statement": 424401000000.0, "Research And Development": 8824050000000.0, "Selling General And Administration": 9644588000000.0, "Selling And Marketing Expense": 7886547000000.0, "General And Administrative Expense": 1758041000000.0, "Gross Profit": 33492127000000.0, "Cost Of Revenue": 52569620000000.0, "Total Revenue": 86061747000000.0, "Operating Revenue": 86061747000000.0}, "2025-06-30": {"Tax Effect Of Unusual Items": -481982401.367308, "Tax Rate For Calcs": 0.111133, "Normalized EBITDA": 20561542000000.0, "Total Unusual Items": -4337000000.0, "Total Unusual Items Excluding Goodwill": -4337000000.0, "Net Income From Continuing Operation Net Minority Interest": 4934034000000.0, "Reconciled Depreciation": 11356722000000.0, "Reconciled Cost Of Revenue": 49069566000000.0, "EBITDA": 20557205000000.0, "EBIT": 9200483000000.0, "Net Interest Income": 901498000000.0, "Interest Expense": 3444354000000.0, "Interest Income": 4345852000000.0, "Normalized Income": 4937889017598.633, "Net Income From Continuing And Discontinued Operation": 4934034000000.0, "Total Expenses": 69890260000000.0, "Total Operating Income As Reported": 4676057000000.0, "Diluted Average Shares": 5881154000.0, "Basic Average Shares": 5881154000.0, "Diluted EPS": 737.0, "Basic EPS": 737.0, "Net Income Common Stockholders": 4934034000000.0, "Net Income": 4934034000000.0, "Minority Interests": -182401000000.0, "Net Income Including Noncontrolling Interests": 5116435000000.0, "Net Income Continuous Operations": 5116435000000.0, "Tax Provision": 639694000000.0, "Pretax Income": 5756129000000.0, "Other Non Operating Income Expenses": -7861000000.0, "Special Income Charges": -4337000000.0, "Other Special Charges": 4337000000.0, "Net Non Operating Interest Income Expense": 901498000000.0, "Total Other Finance Cost": -901498000000.0, "Interest Expense Non Operating": 3444354000000.0, "Interest Income Non Operating": 4345852000000.0, "Operating Income": 4676057000000.0, "Operating Expense": 20820694000000.0, "Depreciation And Amortization In Income Statement": 628848000000.0, "Amortization": 201413000000.0, "Depreciation Income Statement": 427435000000.0, "Research And Development": 9019290000000.0, "Selling General And Administration": 8857672000000.0, "Selling And Marketing Expense": 7062120000000.0, "General And Administrative Expense": 1795552000000.0, "Gross Profit": 25496751000000.0, "Cost Of Revenue": 49069566000000.0, "Total Revenue": 74566317000000.0, "Operating Revenue": 74566317000000.0}, "2025-03-31": {"Tax Effect Of Unusual Items": 51186295256.685844, "Tax Rate For Calcs": 0.10148, "Normalized EBITDA": 20342053000000.0, "Total Unusual Items": 504400000000.0, "Total Unusual Items Excluding Goodwill": 504400000000.0, "Net Income From Continuing Operation Net Minority Interest": 8028407000000.0, "Reconciled Depreciation": 11518790000000.0, "Reconciled Cost Of Revenue": 51009931000000.0, "EBITDA": 20846453000000.0, "EBIT": 9327663000000.0, "Net Interest Income": 1063262000000.0, "Interest Expense": 176087000000.0, "Interest Income": 1239349000000.0, "Normalized Income": 7575193295256.686, "Net Income From Continuing And Discontinued Operation": 8028407000000.0, "Total Expenses": 72455231000000.0, "Total Operating Income As Reported": 6685272000000.0, "Diluted Average Shares": 5921138000.0, "Basic Average Shares": 5920293000.0, "Diluted EPS": 1192.0, "Basic EPS": 1192.0, "Net Income Common Stockholders": 8028407000000.0, "Net Income": 8028407000000.0, "Minority Interests": -194471000000.0, "Net Income Including Noncontrolling Interests": 8222878000000.0, "Net Income Continuous Operations": 8222878000000.0, "Tax Provision": 928698000000.0, "Pretax Income": 9151576000000.0, "Other Non Operating Income Expenses": 877674000000.0, "Special Income Charges": -47899000000.0, "Other Special Charges": 47899000000.0, "Net Non Operating Interest Income Expense": 1063262000000.0, "Total Other Finance Cost": -1482559000000.0, "Interest Expense Non Operating": 176087000000.0, "Interest Income Non Operating": 1239349000000.0, "Operating Income": 6685272000000.0, "Operating Expense": 21445300000000.0, "Depreciation And Amortization In Income Statement": 620547000000.0, "Amortization": 185280000000.0, "Depreciation Income Statement": 435267000000.0, "Research And Development": 9032741000000.0, "Selling General And Administration": 9436601000000.0, "Selling And Marketing Expense": 7732074000000.0, "General And Administrative Expense": 1704527000000.0, "Gross Profit": 28130572000000.0, "Cost Of Revenue": 51009931000000.0, "Total Revenue": 79140503000000.0, "Operating Revenue": 79140503000000.0}, "2024-12-31": {"Tax Effect Of Unusual Items": 2233473281.688778, "Tax Rate For Calcs": 0.019332, "Normalized EBITDA": 19513723000000.0, "Total Unusual Items": 115534000000.0, "Total Unusual Items Excluding Goodwill": 115534000000.0, "Net Income From Continuing Operation Net Minority Interest": 7576133000000.0, "Reconciled Depreciation": 11500570000000.0, "Reconciled Cost Of Revenue": 47268827000000.0, "EBITDA": 19629257000000.0, "EBIT": 8128687000000.0, "Net Interest Income": 1015577000000.0, "Interest Expense": 221432000000.0, "Interest Income": 1237009000000.0, "Normalized Income": 7462832473281.688, "Net Income From Continuing And Discontinued Operation": 7576133000000.0, "Total Expenses": 69295566000000.0, "Total Operating Income As Reported": 6492703000000.0, "Diluted Average Shares": null, "Basic Average Shares": null, "Diluted EPS": null, "Basic EPS": null, "Net Income Common Stockholders": 7576133000000.0, "Net Income": 7576133000000.0, "Minority Interests": -178261000000.0, "Net Income Including Noncontrolling Interests": 7754394000000.0, "Net Income Continuous Operations": 7754394000000.0, "Tax Provision": 152861000000.0, "Pretax Income": 7907255000000.0, "Other Non Operating Income Expenses": 54968000000.0, "Special Income Charges": -50149000000.0, "Other Special Charges": 50149000000.0, "Net Non Operating Interest Income Expense": 1015577000000.0, "Total Other Finance Cost": null, "Interest Expense Non Operating": 221432000000.0, "Interest Income Non Operating": 1237009000000.0, "Operating Income": 6492703000000.0, "Operating Expense": 22026739000000.0, "Depreciation And Amortization In Income Statement": 617424000000.0, "Amortization": 184056000000.0, "Depreciation Income Statement": 433368000000.0, "Research And Development": 10262019000000.0, "Selling General And Administration": 8882058000000.0, "Selling And Marketing Expense": 6976676000000.0, "General And Administrative Expense": 1905382000000.0, "Gross Profit": 28519442000000.0, "Cost Of Revenue": 47268827000000.0, "Total Revenue": 75788269000000.0, "Operating Revenue": 75788269000000.0}, "2024-09-30": {"Tax Effect Of Unusual Items": null, "Tax Rate For Calcs": null, "Normalized EBITDA": null, "Total Unusual Items": null, "Total Unusual Items Excluding Goodwill": null, "Net Income From Continuing Operation Net Minority Interest": null, "Reconciled Depreciation": null, "Reconciled Cost Of Revenue": null, "EBITDA": null, "EBIT": null, "Net Interest Income": null, "Interest Expense": null, "Interest Income": null, "Normalized Income": null, "Net Income From Continuing And Discontinued Operation": null, "Total Expenses": null, "Total Operating Income As Reported": null, "Diluted Average Shares": 6792740972.0, "Basic Average Shares": 6792740972.0, "Diluted EPS": 1440.0, "Basic EPS": 1440.0, "Net Income Common Stockholders": null, "Net Income": null, "Minority Interests": null, "Net Income Including Noncontrolling Interests": null, "Net Income Continuous Operations": null, "Tax Provision": null, "Pretax Income": null, "Other Non Operating Income Expenses": null, "Special Income Charges": null, "Other Special Charges": null, "Net Non Operating Interest Income Expense": null, "Total Other Finance Cost": null, "Interest Expense Non Operating": null, "Interest Income Non Operating": null, "Operating Income": null, "Operating Expense": null, "Depreciation And Amortization In Income Statement": null, "Amortization": null, "Depreciation Income Statement": null, "Research And Development": null, "Selling General And Administration": null, "Selling And Marketing Expense": null, "General And Administrative Expense": null, "Gross Profit": null, "Cost Of Revenue": null, "Total Revenue": null, "Operating Revenue": null}}, "info": {"longName": "Samsung Electronics Co., Ltd.", "sector": "Technology", "industry": "Consumer Electronics", "longBusinessSummary": "Samsung Electronics Co., Ltd. engages in the consumer electronics, information technology and mobile communications, and device solutions businesses worldwide. The company operates through four divisions: Device eXperience (DX), Device Solutions (DS), SDC, and Harman. The company offers smartphones, tablets, audio sounds, watches, switches, and accessories; TVs, and sound devices; appliances, including refrigerators, washing machines and dryers, vacuum cleaners, cooking appliances, dishwashers, air conditioners, and air purifiers; monitors and memory storage products; displays, and smart and LED signages; and other accessories. It also engages in venture capital investments, cloud services, network devices installation, semiconductor equipment services, digital advertising platforms, marketing, consulting, connected services provider, logistics, financing, and software design activities. In addition, the company provides toll processing and sales of semiconductors and display panels; development and sale of network solutions; manufacture of semiconductors and food; the provision of repair services for electronic devices; and development and supply of semiconductor process defect and quality control software, as well as digital televisions, foundry, system large scale integration (LSI). Further, it provides connected car systems, audio and visual products, enterprise automation solutions, and connected services. Samsung Electronics Co., Ltd. was incorporated in 1969 and is based in Suwon-si, South Korea.", "financialCurrency": "KRW", "totalRevenue": 388405938618368, "grossProfits": 185170418204672, "operatingIncome": null, "netIncomeToCommon": 83360953139200, "country": "South Korea"}, "currency": "KRW", "usd_rate": 0.0006703311228193343}}